Workbook

Sheet LEEME
B2: CRM COMERCIAL — KATANA + KIF
B3: Un solo archivo. Un solo pipeline. Se revisa cada lunes.
B6: CÓMO USARLO
B7: 1. LEADS | C7: Todo contacto vive aquí. Un renglón = una persona (no una empresa). Vacía primero tus bases existentes.
B8: 2. PIPELINE | C8: Solo deals con propuesta enviada o en negociación. Aquí se ve el dinero vs. la meta mensual.
B9: 3. TALENTOS | C9: Roster con verticales y estatus de media kit. Alimenta los dropdowns.
B10: 4. MARCAS TARGET | C10: El mapa de scouting por vertical (lo iremos llenando juntos, vertical por vertical).
B11: 5. AGENCIAS | C11: Agencias que manejan influencer marketing de las marcas target.
B12: 6. DASHBOARD | C12: Resumen automático: leads por estatus, dinero en pipeline vs. obligación mensual.
B13: 7. CATALOGOS | C13: Listas que alimentan los dropdowns. Si agregas un vertical o estatus nuevo, se agrega aquí.
B15: REGLAS DE ORO
B16: Regla 1 | C16: Ningún lead sin "Próximo paso" y fecha. Un lead sin próximo paso es un lead muerto.
B17: Regla 2 | C17: Tibio antes que frío: primero se trabaja la gente que ya te conoce.
B18: Regla 3 | C18: Meta viva: 8 propuestas activas en PIPELINE, siempre.
B19: Regla 4 | C19: Lunes = 20 min de revisión del DASHBOARD. Nada más.

Sheet HISTORIAL TALENTOS
A1: Fecha | B1: Talento | C1: Campo | D1: Valor anterior | E1: Valor nuevo | F1: Usuario | G1: Fuente | H1: Tipo de cambio | I1: Fila TALENTOS | J1: Request ID

Sheet PERFIL COMERCIAL — CAPTURA
A1: Llena SOLO las columnas D a H. El id, los nombres y el folder son técnicos: no los edites. Esta hoja NO captura estadísticas ni tarifas — esas viven en sus propias fuentes. NUNCA inventes logros, marcas ni cifras: si no lo puedes comprobar, déjalo vacío.
A2: talent_id | B2: canonical_name | C2: display_name | D2: Biografía breve | E2: Logros principales | F2: Colaboraciones y campañas | G2: Links de campañas exitosas | H2: Marcas relacionadas | I2: source_status | J2: library_folder_id | K2: Responsable | L2: Última actualización
A3: EJEMPLO | B3: — borrar esta fila — | C3: — borrar — | D3: [Qué hace, por qué importa, qué lo hace distinto. 40-60 palabras. Sin adjetivos vacíos.] | E3: [3 a 5 logros comprobables, separados por punto y coma. Con año cuando exista.] | F3: [Solo acuerdos REALES, separados por punto y coma. Una plática no es una colaboración.] | G3: [URLs publicadas, una por línea. Sin link, no va la campaña.] | H3: [Marcas afines a las que le pega, aunque no haya trabajado con ellas. Esta sí es aspiracional.] | I3: PENDIENTE
A4: KT-001 | B4: Divino Espinoza | C4: Divino Espinoza | I4: PENDIENTE | J4: 1LJV7J41pYCuLaLkPNYVRdIrqWKMBjRgm | K4: Jesús
A5: KT-002 | B5: Lazy Boy | C5: Lazy Boy | I5: PENDIENTE | J5: 1FJuLZ5coA36tdK4eDM8uTqnwMNm872hm | K5: Jesús
A6: KT-003 | B6: Luis Pride | C6: Luis Pride | I6: PENDIENTE | J6: 1UjZkcQ_T4pLVxujZhh4ME1fP87N-4gby | K6: Jesús
A7: KT-004 | B7: Ronaldo BXM | C7: Ronaldo BXM | I7: PENDIENTE | J7: 1aA5WfpiPjF3tAhzTxXIQmu7MuryCVeuo | K7: Jesús
A8: KT-005 | B8: Tejon de la Miel | C8: Tejón de la Miel | I8: PENDIENTE | J8: 1la5czIUdiZO1ilJxnaMHSNObFjeE0jhC | K8: Jesús
A9: KT-006 | B9: Mama Tejona | C9: Mamá Tejona | I9: PENDIENTE | J9: 10wR2gldOS8ouOiHJwtIS4fr1hES1mRuc | K9: Jesús
A10: KT-007 | B10: Cesar de la Parra | C10: César de la Parra | I10: PENDIENTE | J10: 1Nzq8tDH1gPeE5uOgpOaD0SELM6PaAsTp | K10: Jesús
A11: KT-008 | B11: Mar Coronel | C11: Mar Coronel | I11: PENDIENTE | J11: 1saKx4zCLWHkzv8t_U7UYfY684cXkcjpA | K11: Jesús
A12: KT-009 | B12: Nene Creative | C12: Nene Creative | I12: PENDIENTE | J12: 1SqyS83UWl7ZDs_YZSaEIFw8seoO7gcp7 | K12: Jesús
A13: KT-010 | B13: Julio Orozco | C13: Julio Orozco | I13: PENDIENTE | J13: 1MAsj4wz6UrtFjt_fvL8EIq4rPA57mWMx | K13: Jesús
A14: KT-011 | B14: Mariel Estrella | C14: Mariel Estrella | I14: PENDIENTE | J14: 1ckIvy8oUklftpUARy2DuyYQowggb-MaP | K14: Jesús
A15: KT-012 | B15: Tony Gastelum | C15: Tony Gastélum | I15: PENDIENTE | J15: 1hXOEB4LV3icf6uO-otLv1m_DYXXHRCf0 | K15: Jesús
... A24: KT-028 | B24: Padigol | C24: Padigol | I24: PENDIENTE | J24: 1DZO6m1Om0i5NIYPDgLYkTZeT5B4YkbM9 | K24: Jesús

Sheet DASHBOARD
B2: DASHBOARD COMERCIAL
B3: Se actualiza solo. Revisar cada lunes, 20 minutos.
B5: OBLIGACIÓN MENSUAL (MXN) | C5: 140000 | D5: ← Editable (Rivaldo). Si se renegocia, cámbialo aquí. | F5: LEADS ACTIVOS SIN PRÓXIMO PASO | G5: =COUNTIFS(LEADS!B:B,"<>",LEADS!R:R,"",LEADS!P:P,"<>Cerrado GANADO",LEADS!P:P,"<>Cerrado PERDIDO",LEADS!P:P,"<>Dormido") -> 1
F6: Meta: 0. Un lead sin próximo paso es un lead muerto.
B7: PROPUESTAS ACTIVAS (meta: 8) | C7: =COUNTIF(PIPELINE!F:F,"Propuesta enviada")+COUNTIF(PIPELINE!F:F,"Negociación")+COUNTIF(PIPELINE!F:F,"Contrato") -> 2
B8: FEE EN PIPELINE (total, MXN) | C8: =SUMIFS(PIPELINE!I:I,PIPELINE!F:F,"<>Cerrado PERDIDO",PIPELINE!F:F,"<>Cerrado GANADO",PIPELINE!F:F,"<>") -> 230000
B9: FEE PONDERADO (realista, MXN) | C9: =SUMIFS(PIPELINE!J:J,PIPELINE!F:F,"<>Cerrado PERDIDO",PIPELINE!F:F,"<>Cerrado GANADO",PIPELINE!F:F,"<>") -> 137500
B10: GANADO (fee cerrado, MXN) | C10: =SUMIFS(PIPELINE!I:I,PIPELINE!F:F,"Cerrado GANADO") -> 120000
B12: FEE PONDERADO POR MES DE COBRO | F12: LEADS POR ESTATUS
B13: Mes | C13: Fee ponderado | D13: vs. obligación | F13: Estatus | G13: Cuenta
B14: Jul 2026 | C14: =SUMIFS(PIPELINE!J:J,PIPELINE!L:L,B14,PIPELINE!F:F,"<>Cerrado PERDIDO") -> 0 | D14: =IF(C14="","",C14-$C$5) -> -140000 | F14: Por contactar | G14: =COUNTIF(LEADS!P:P,F14) -> 1
B15: Ago 2026 | C15: =SUMIFS(PIPELINE!J:J,PIPELINE!L:L,B15,PIPELINE!F:F,"<>Cerrado PERDIDO") -> 0 | D15: =IF(C15="","",C15-$C$5) -> -140000 | F15: Contactado | G15: =COUNTIF(LEADS!P:P,F15) -> 0
B16: Sep 2026 | C16: =SUMIFS(PIPELINE!J:J,PIPELINE!L:L,B16,PIPELINE!F:F,"<>Cerrado PERDIDO") -> 0 | D16: =IF(C16="","",C16-$C$5) -> -140000 | F16: En conversación | G16: =COUNTIF(LEADS!P:P,F16) -> 1
B17: Oct 2026 | C17: =SUMIFS(PIPELINE!J:J,PIPELINE!L:L,B17,PIPELINE!F:F,"<>Cerrado PERDIDO") -> 0 | D17: =IF(C17="","",C17-$C$5) -> -140000 | F17: Reunión agendada | G17: =COUNTIF(LEADS!P:P,F17) -> 0
B18: Nov 2026 | C18: =SUMIFS(PIPELINE!J:J,PIPELINE!L:L,B18,PIPELINE!F:F,"<>Cerrado PERDIDO") -> 0 | D18: =IF(C18="","",C18-$C$5) -> -140000 | F18: Propuesta enviada | G18: =COUNTIF(LEADS!P:P,F18) -> 0
B19: Dic 2026 | C19: =SUMIFS(PIPELINE!J:J,PIPELINE!L:L,B19,PIPELINE!F:F,"<>Cerrado PERDIDO") -> 0 | D19: =IF(C19="","",C19-$C$5) -> -140000 | F19: Negociación | G19: =COUNTIF(LEADS!P:P,F19) -> 0
B20: Ene 2027 | C20: =SUMIFS(PIPELINE!J:J,PIPELINE!L:L,B20,PIPELINE!F:F,"<>Cerrado PERDIDO") -> 0 | D20: =IF(C20="","",C20-$C$5) -> -140000 | F20: Cerrado GANADO | G20: =COUNTIF(LEADS!P:P,F20) -> 0
F21: Cerrado PERDIDO | G21: =COUNTIF(LEADS!P:P,F21) -> 0
F22: Dormido | G22: =COUNTIF(LEADS!P:P,F22) -> 0

Sheet CATALOGOS
A1: VERTICALES | B1: TIPO DE LEAD | C1: ESTATUS LEAD | D1: TEMPERATURA | E1: PRIORIDAD | F1: UNIDAD DE NEGOCIO | G1: TALENTOS | H1: RESPONSABLE | I1: ETAPA DEAL | J1: PROBABILIDAD
A2: Bebidas | B2: Marca directa | C2: Por contactar | D2: Caliente (ya trabajamos) | E2: P1 - Esta semana | F2: KIF (campañas) | G2: Pool Combate (paquete) | H2: Chuy | I2: Propuesta enviada | J2: 25%
A3: Alimentos & Gastro | B3: Agencia creativa | C3: Contactado | D3: Tibio (nos conoce) | E3: P2 - Este mes | F3: Katana (talento casa) | G3: Divino Espinoza | H3: Ramiro | I3: Negociación | J3: 50%
A4: Apuestas & Fantasy | B4: Agencia de medios | C4: En conversación | D4: Frío (scouting) | E4: P3 - Después | F4: FIERA | G4: Lacy Way | H4: Paty | I4: Contrato | J4: 75%
A5: Tech & Telecom | B5: Agencia influencer mkt | C5: Reunión agendada | F5: Fórmula S | G5: Luis Pride | H5: Otro | I5: Cerrado GANADO | J5: 90%
A6: Gaming & Esports | B6: Agencia PR | C6: Propuesta enviada | F6: DOPA/Park8 | G6: Ronny | I6: Cerrado PERDIDO
A7: Sportswear & Nutrición | B7: BTL / Experiential | C7: Negociación | G7: Tejón de la Miel
A8: Belleza & Wellness | B8: Productora | C8: Cerrado GANADO | G8: Tejón + Mamá (dupla familiar)
A9: Streaming & Entretenimiento | B9: Plataforma | C9: Cerrado PERDIDO | G9: César de la Parra
A10: Familia & Kids | B10: Sponsor | C10: Dormido | G10: Mar Coronel
A11: Financiero & Fintech | B11: Aliado comercial | G11: Nene Creative
A12: Otro | G12: Julio Orozco
G13: Mariel Estrella
G14: Mariely
G15: Talento aliado (externo)
G16: Varios / Pool mixto

Sheet LEADS
A1: SEÑALÉTICA: | B1: ACTIVO — ya hay contacto real / cerrado | C1: A UN PASO — contrato / por firmar | D1: EN PROCESO — negociación / propuesta / tibio | E1: FRÍO — target, aún sin contactar | F1: PERDIDO / DORMIDO — reactivar o descartar
A2: ID | B2: Empresa | C2: Tipo | D2: Vertical | E2: Contacto (nombre) | F2: Cargo | G2: Email | H2: Teléfono / WhatsApp | I2: LinkedIn | J2: Ciudad | K2: Temperatura | L2: Prioridad | M2: Unidad de negocio | N2: Talento recomendado | O2: Idea de campaña / ángulo | P2: Estatus | Q2: Último contacto | R2: Próximo paso | S2: Fecha próximo paso | T2: Responsable | U2: Fuente | V2: Notas
A3: =IF(B2="","","L"&TEXT(ROW()-1,"000")) -> L002 | B3: Cerveza Victoria | C3: Marca directa | D3: Bebidas | E3: (nombre del contacto) | F3: Brand Manager | J3: CDMX | K3: Tibio (nos conoce) | L3: P1 - Esta semana | M3: KIF (campañas) | N3: Pool Combate (paquete) | O3: Pool combate + activación en función | P3: Por contactar | R3: Mandar media kit y pedir llamada | T3: Chuy | U3: Relación previa | V3: EJEMPLO — borra este renglón
A4: L003 | B4: Paramount Pictures | C4: Plataforma | D4: Streaming & Entretenimiento | E4: Aureliano “Aure” Domínguez / María Constela Olivares | F4: PR / Películas (cargo exacto pendiente) | G4: Aureliano_Dominguez@paramount.com / Maria.ConstelaOlivares@paramount.com | J4: CDMX | K4: Tibio (nos conoce) | L4: P2 - Este mes | M4: Katana (talento casa) | N4: Varios / Pool mixto | O4: PR por estreno: premieres, junkets, experiencias y contenido con talento según cada película. Street Fighter en seguimiento. | P4: En conversación | Q4: 2026-08-03 | R4: Esperar respuesta de Aure sobre Street Fighter y pedir próximos títulos/oportunidades de PR. Solicitar de nuevo enlace con Félix por separado. | T4: Chuy | U4: Relación directa / junta Paramount 2026-06-03 | V4: Relación principalmente de PR y normalmente sin paga; ocasionalmente puede haber presupuesto. No existe calendario de estrenos ni fechas confirmadas en las fuentes. Mantener Paramount Películas separado de Paramount Social/UFC.
A5: =IF(B4="","","L"&TEXT(ROW()-1,"000")) -> L004
A6: =IF(B5="","","L"&TEXT(ROW()-1,"000"))
A7: =IF(B6="","","L"&TEXT(ROW()-1,"000"))
A8: =IF(B7="","","L"&TEXT(ROW()-1,"000"))
A9: =IF(B8="","","L"&TEXT(ROW()-1,"000"))
A10: =IF(B9="","","L"&TEXT(ROW()-1,"000"))
A11: =IF(B10="","","L"&TEXT(ROW()-1,"000"))
A12: =IF(B11="","","L"&TEXT(ROW()-1,"000"))
A13: =IF(B12="","","L"&TEXT(ROW()-1,"000"))
A14: =IF(B13="","","L"&TEXT(ROW()-1,"000"))
A15: =IF(B14="","","L"&TEXT(ROW()-1,"000"))
A16: =IF(B15="","","L"&TEXT(ROW()-1,"000"))
... A501: =IF(B500="","","L"&TEXT(ROW()-1,"000"))

Sheet PIPELINE
A1: SEÑALÉTICA: | B1: ACTIVO — ya hay contacto real / cerrado | C1: A UN PASO — contrato / por firmar | D1: EN PROCESO — negociación / propuesta / tibio | E1: FRÍO — target, aún sin contactar | F1: PERDIDO / DORMIDO — reactivar o descartar
A2: ID Deal | B2: Empresa | C2: Unidad de negocio | D2: Talento | E2: Descripción del deal | F2: Etapa | G2: Probabilidad | H2: Monto total (MXN) | I2: Fee neto Katana/KIF (MXN) | J2: Fee ponderado (MXN) | K2: Mes de cierre esperado | L2: Mes de cobro esperado | M2: Responsable | N2: Próximo paso | O2: Fecha próximo paso | P2: Notas
A3: =IF(B3="","","D"&TEXT(ROW()-2,"000")) -> D001 | B3: Gatorade (vía Affluency / FCO Group) | C3: KIF (campañas) | D3: Mariel Estrella | E3: Propuesta preliminar para Gatorade dirigida a Gen Z y Millennials. Scope solicitado: 1 Reel + 1 TikTok + 1 mes de pauta + 1 mes de exclusividad. Afluency preguntó si podía cerrarse en $120,000 MXN; Chuy indicó que $140,000 MXN sería el mínimo viable y aclaró que la propuesta previa no incluía pauta ni exclusividad. | F3: Negociación preliminar / sin brief final | G3: 50% | H3: 140000 | I3: 140000 | J3: 70000 | K3: Ago 2026 | M3: Chuy | N3: Esperar brief formal y respuesta de Gatorade/Affluency. No aprobar $120,000 MXN sin revisar exactamente si Reel y TikTok son piezas distintas o espejo, así como términos de pauta y exclusividad. | O3: 2026-08-04 | P3: Evidencia por WhatsApp: objetivo de awareness para Gen Z y Millennials; scope preliminar de 1 Reel, 1 TikTok, 1 mes de pauta y 1 mes de exclusividad. Afluency propuso $120,000 MXN o dos Reels; Chuy señaló $140,000 MXN como máximo ajuste posible dentro de precio paquete. Brief aún no disponible. No marcar como aprobado, cerrado ni tarifa final autorizada hasta recibir brief y confirmar derechos.
A4: =IF(B4="","","D"&TEXT(ROW()-2,"000")) -> D002 | B4: Canal MX (vía agencia Padrinito) | C4: KIF (campañas) | D4: Wereverwero | E4: Audio — campaña Canal MX | F4: Cerrado GANADO | G4: 100% | H4: 90000 | I4: 90000 | J4: =IF(OR(I4="",G4=""),"",I4*VALUE(SUBSTITUTE(G4,"%",""))/100) -> 90000 | K4: Jul 2026 | L4: Ramiro | M4: Dar seguimiento a entrega (Wereverwero "no tarda") | N4: Cerrado por Ramiro
A5: =IF(B5="","","D"&TEXT(ROW()-2,"000")) -> D003 | B5: Canal MX (vía agencia Padrinito) | C5: KIF (campañas) | D5: Mike Máquina del Mal | E5: Audio — campaña Canal MX | F5: Cerrado GANADO | G5: 100% | H5: 30000 | I5: 30000 | J5: =IF(OR(I5="",G5=""),"",I5*VALUE(SUBSTITUTE(G5,"%",""))/100) -> 30000 | K5: Jul 2026 | L5: Ramiro | M5: Confirmar entrega recibida y facturar | N5: Cerrado por Ramiro. Monto aprox. ("creo 30 mil") — confirmar exacto
A6: =IF(B6="","","D"&TEXT(ROW()-2,"000")) -> D004 | B6: Canal MX (vía agencia Padrinito) | C6: KIF (campañas) | D6: Mercedes Roa | E6: Audio — campaña Canal MX | F6: Negociación | G6: 75% | H6: 90000 | I6: 90000 | J6: =IF(OR(I6="",G6=""),"",I6*VALUE(SUBSTITUTE(G6,"%",""))/100) -> 67500 | K6: Ago 2026 | L6: Ramiro | M6: Cerrar monto y firmar
A7: D006 | B7: VERSUS BET (vía VKNG Group) | C7: Katana (talento casa) | D7: Tony Gastélum | E7: 1 TikTok + espejo en Instagram Reels + derechos de pauta en TikTok por 30 días | F7: Negociación | G7: 0.75 | H7: 35000 | K7: Ago 2026 | M7: Ramiro | N7: Negociar el cierre en $45,000 MXN y confirmar condiciones finales con VKNG Group / VERSUS BET | O7: 2026-08-04 | P7: Condición corregida: pago a 90 días hábiles. Tony ya aceptó $35,000 MXN como punto de partida. Ramiro busca subir el deal a $45,000 MXN. Responsable comercial: Ramiro. Mantener como negociación hasta confirmación final del cliente.
A8: D007 | B8: Gamergy | C8: Katana (talento casa / IP) | D8: Nene Creative | E8: Propuesta de seguimiento para llegar con concepto de torneo de FC Mobile + participación de Nene Creative. | F8: En proceso — seguimiento / propuesta por desarrollar | G8: 35% | K8: Ago 2026 | M8: Chuy | N8: Dar seguimiento a Gamergy y preparar propuesta concreta de torneo FC Mobile con Nene Creative. | P8: No inventar presupuesto, alcance ni derechos. Definir formato del torneo, rol de Nene, fechas, sede/plataforma, producción y patrocinadores antes de cotizar.
A9: D008 | B9: Goodyear | C9: KIF (campañas) | D9: Por definir | E9: Campaña con presupuesto total de $120,000 MXN. Se evalúan uno o varios talentos para cubrir el alcance dentro del presupuesto. | F9: En proceso — armado de opciones | G9: 35% | H9: 120000 | K9: Ago 2026 | M9: Ramiro | N9: Definir qué talento puede cubrir todo el alcance por $120,000 MXN y armar una o varias opciones para presentar. | P9: Perfiles revisados: Chuy Almada, Ronny BXM, Luis Pride, Juan de Dios García y Yozz. No hay talento seleccionado ni propuesta aprobada. Ramiro acomodará entregables y propondrá la mejor opción dentro del presupuesto. Confirmar si el monto incluye IVA, pauta y derechos.
A10: D009 | B10: Banx / Banxs (Gera) | C10: Katana — PR, lanzamiento e influencers | D10: Por definir | E10: Nuevo banco o neobanco próximo a lanzarse al mercado. Posible iguala para dar a conocer el producto, generar conversiones y aperturas de cuenta mediante PR, líderes de opinión e influencers. | F10: Descubrimiento — reunión inicial | K10: Ago 2026 | M10: Chuy | N10: Escuchar objetivos, producto, audiencia, fecha de lanzamiento, alcance esperado, KPIs, presupuesto y duración de la posible iguala. Definir siguiente paso para propuesta. | O10: 2026-08-04 | P10: No asumir todavía que el alcance está cerrado. Confirmar nombre comercial, estatus regulatorio, funcionalidades disponibles, mensajes permitidos, responsables internos y si buscan campaña puntual o iguala mensual. No prometer talentos, métricas ni resultados antes del brief.
A11: D010 | B11: Supernova — Luis Pride | C11: Katana — talento / negociación | D11: Luis Pride | E11: Negociación para participación de Luis Pride en Supernova. Alan Tamayo ofreció $500,000 MXN; Chuy abrió en $550,000 MXN y buscará mejorar la oferta antes de cerrar. | F11: Negociación activa | G11: 0.75 | H11: 500000 | K11: Ago 2026 | M11: Chuy | N11: Esperar respuesta de Alan Tamayo, empujar la cifra por arriba de $500,000 MXN y cerrar condiciones finales con Luis Pride. | O11: 2026-08-04 | P11: Oferta actual confirmada: $500,000 MXN. Ancla inicial de Chuy: $550,000 MXN. Antes de cerrar, confirmar IVA, viáticos, hospedaje, exclusividad, derechos de imagen, publicaciones, apariciones previas, forma de pago, cancelación y penalizaciones. No marcar como cerrado hasta tener aceptación y condiciones completas.
A12: D011 | B12: Supernova — Gera MX vs Lit Killah | C12: Katana — talento / negociación | D12: Gera MX | E12: Oportunidad para cerrar a Gera MX como rival de Lit Killah en Supernova. Lit Killah ya está puesto. Chuy llevará directamente el cierre y la negociación de Gera MX. | F12: Contacto iniciado / negociación por abrir | G12: 0.35 | K12: Ago 2026 | M12: Chuy | N12: Dar seguimiento a Durán, personal manager de Gera MX, para confirmar interés formal, disponibilidad y expectativa económica; después abrir negociación y cerrar a Gera. | O12: 2026-08-05 | P12: Lit Killah está confirmado y dispuesto. Mensaje ya enviado a Durán. No registrar la pelea como cerrada hasta tener aceptación formal de Gera MX y acuerdo económico y contractual.
A13: =IF(B13="","","D"&TEXT(ROW()-2,"000")) | J13: =IF(OR(I13="",G13=""),"",I13*VALUE(SUBSTITUTE(G13,"%",""))/100)
A14: =IF(B14="","","D"&TEXT(ROW()-2,"000")) | J14: =IF(OR(I14="",G14=""),"",I14*VALUE(SUBSTITUTE(G14,"%",""))/100)
A15: =IF(B15="","","D"&TEXT(ROW()-2,"000")) | J15: =IF(OR(I15="",G15=""),"",I15*VALUE(SUBSTITUTE(G15,"%",""))/100)
A16: =IF(B16="","","D"&TEXT(ROW()-2,"000")) | J16: =IF(OR(I16="",G16=""),"",I16*VALUE(SUBSTITUTE(G16,"%",""))/100)
A17: =IF(B17="","","D"&TEXT(ROW()-2,"000")) | J17: =IF(OR(I17="",G17=""),"",I17*VALUE(SUBSTITUTE(G17,"%",""))/100)
A18: =IF(B18="","","D"&TEXT(ROW()-2,"000")) | J18: =IF(OR(I18="",G18=""),"",I18*VALUE(SUBSTITUTE(G18,"%",""))/100)
A19: =IF(B19="","","D"&TEXT(ROW()-2,"000")) | J19: =IF(OR(I19="",G19=""),"",I19*VALUE(SUBSTITUTE(G19,"%",""))/100)
A20: =IF(B20="","","D"&TEXT(ROW()-2,"000")) | J20: =IF(OR(I20="",G20=""),"",I20*VALUE(SUBSTITUTE(G20,"%",""))/100)
A21: =IF(B21="","","D"&TEXT(ROW()-2,"000")) | J21: =IF(OR(I21="",G21=""),"",I21*VALUE(SUBSTITUTE(G21,"%",""))/100)
A22: =IF(B22="","","D"&TEXT(ROW()-2,"000")) | J22: =IF(OR(I22="",G22=""),"",I22*VALUE(SUBSTITUTE(G22,"%",""))/100)
A23: =IF(B23="","","D"&TEXT(ROW()-2,"000")) | J23: =IF(OR(I23="",G23=""),"",I23*VALUE(SUBSTITUTE(G23,"%",""))/100)
A24: =IF(B24="","","D"&TEXT(ROW()-2,"000")) | J24: =IF(OR(I24="",G24=""),"",I24*VALUE(SUBSTITUTE(G24,"%",""))/100)
... A251: =IF(B251="","","D"&TEXT(ROW()-2,"000")) | J251: =IF(OR(I251="",G251=""),"",I251*VALUE(SUBSTITUTE(G251,"%",""))/100)

Sheet TALENTOS
A1: Talento | B1: Categoría | C1: Verticales que abre | D1: Tipo (casa / aliado) | E1: IG seguidores | F1: TikTok seguidores | G1: YouTube subs | H1: Otras plataformas | I1: Media kit HTML | J1: Tarifa base referencia (MXN) | K1: Notas / ángulo comercial | V1: País / mercado | W1: Estatus network | X1: Prioridad comercial | Y1: Disponibilidad | Z1: Foto principal | AA1: Bio corta | AB1: Campañas / casos | AC1: Logros | AD1: Videos | AE1: Fecha de corte métricas | AF1: Fuente métricas | AG1: Notas operativas | AH1: Última actualización | AI1: Actualizado por
A2: Luis Pride | B2: MMA | C2: Bebidas, Apuestas, Sportswear, Nutrición | D2: KATANA — Casa | I2: Pendiente | J2: Ver Tarifario Maestro 2026 | K2: Activo premium de box. La cifra de $750,000 MXN aplica como referencia para presencia de marca en el short durante el combate. Puede ampliarse a ropa de entrenamiento, llegada, pesaje, conferencia o contenido asociado según el paquete. Sujeto a evento, rival, transmisión, ubicación del logo, derechos, exclusividad y aprobación final. Fuente: definición interna Chuy, 31-jul-2026. Pendiente aprobación de Ramiro.
A3: Ronny | B3: Box / Creator / Coach | C3: Box, Combate, Sportswear, Nutrición, Apuestas, Bebidas, Fitness | D3: KATANA — Casa | E3: 958000 | F3: 1100000 | G3: 23300 | H3: Twitch principal | Kick disponible | I3: https://drive.google.com/file/d/1TWMAP6Ak43b1IMU3mSScKstMW9jvHAjA/view | J3: Ver Tarifario Maestro 2026 | K3: PILOTO — FASE 1. Métricas capturadas del roster operativo: Instagram 958K, TikTok 1.1M y YouTube 23.3K; requieren validación de fecha de corte antes de usarse con cliente. Media kit V1 localizado en Drive. Existen al menos tres copias del mismo HTML; pendiente declarar una sola versión maestra y archivar duplicados. Tarifario en revisión de Ramiro. | X3: PILOTO — FASE 1
A4: Tejón de la Miel | B4: Box — Promesa | C4: Familia & Kids, Sportswear, Alimentos | D4: KATANA — Casa | I4: Pendiente | J4: Ver Tarifario Maestro 2026 | K4: Regla de espejo aplicada: 1.5x el precio más alto entre TikTok y Reel IG. Fee base por pelear: $450,000 MXN. Fuente: definición interna Chuy, 31-jul-2026.
A5: Divino Espinoza | B5: Box — Campeón del mundo | C5: Bebidas, Apuestas, Sportswear, Streaming | D5: KATANA — Casa | I5: Pendiente | J5: Caso por caso | K5: Streamer también activo en Twitch. La tarifa de stream registrada corresponde a Twitch. Fee base por pelear: $250,000 MXN. Fuente: Tabulador HONOR + ajustes internos de Chuy, 31-jul-2026. Propuesta interna pendiente de aprobación de Ramiro.
A6: Lazy Boy | B6: MMA / UFC | C6: Bebidas, Apuestas, Sportswear, Grooming | D6: KATANA — Aliado (definir) | I6: Pendiente | J6: Caso por caso | K6: TikTok igual a Mariel Estrella. Reel IG corregido a $150,000 y Reel Collab a $180,000. Peleas desde $50,000 MXN, sujeto a rival, evento, transmisión, ciudad, viáticos, exposición de marca y condiciones deportivas. Menor de edad: requiere autorización de tutor, revisión legal y aprobación interna. Fuente: definición interna Chuy, 31-jul-2026. Pendiente aprobación de Ramiro.
A7: César de la Parra | B7: Chef — Alto perfil | C7: Alimentos & Gastro, Bebidas, Electrodomésticos, Delivery, Turismo | D7: KATANA — Acceso exclusivo | I7: Pendiente | J7: Caso por caso | K7: Perfil altamente selectivo. Solo considerar marcas con afinidad real y aprobación expresa del talento. Priorizar acuerdos anuales, embajadurías de largo plazo o proyectos extraordinarios con alto valor creativo, gastronómico o reputacional. No manejar tarifario estándar ni cotizar por pieza aislada salvo excepción estratégica. Fuente: definición interna Chuy, 31-jul-2026. Requiere revisión de Jesús y Ramiro antes de presentar.
A8: Mariel Estrella | B8: Fitness / Lifestyle / Wellness | C8: Fitness, Wellness, Sportswear, Belleza, Healthy food | D8: KATANA — Casa | I8: Pendiente | J8: Ver Tarifario Maestro 2026 | K8: PENDIENTE: completar bio, propuesta de valor, plataformas, métricas, assets, casos y restricciones. La nota anterior de pronósticos/apuestas no correspondía a este perfil. | X8: PILOTO — FASE 1
A9: Mariely Coronel | B9: Fútbol | C9: Apuestas, Bebidas, Snacks, Telcos | D9: KATANA — Casa | I9: Pendiente | J9: Ver Tarifario Maestro 2026 | K9: Twitch es su plataforma principal de streaming. Stream dedicado para marca: $120,000 MXN por hora. Integraciones dentro de streams existentes se cotizan caso por caso. YouTube disponible: video dedicado, integración y Short; tarifas pendientes. Fuente: definición interna Chuy, 31-jul-2026. Pendiente aprobación de Ramiro.
A10: Nene Creative | B10: Gaming / Esports / Streaming | C10: Gaming, Esports, Tech, Telecom, Automotriz, Energy | D10: KATANA — Casa | H10: Kick | Twitch | YouTube | I10: Pendiente | J10: Ver Tarifario Maestro 2026 | K10: Kick es su plataforma principal de streaming. YouTube disponible: video dedicado, integración dentro de video y Short; tarifas pendientes. Fuente: definición interna Chuy, 31-jul-2026. Propuesta interna pendiente de aprobación de Ramiro. | X10: PILOTO — FASE 1
A11: Julio Orozco | B11: Música / Podcast / IRL | C11: Bebidas, Festivales, Ticketing, Moda, Nightlife | D11: KATANA — Casa | H11: Kick | YouTube | I11: Pendiente | J11: Ver Tarifario Maestro 2026 | K11: Cierres en curso — empujar.
A12: Juan de Dios García | B12: Storytime / Vlogging | C12: Entretenimiento, Bebidas, Apps | D12: KATANA — Operable | H12: @juanddiosg | I12: Pendiente | J12: Ver Tarifario Maestro 2026 | K12: POSIBLE DUPLICADO: ¿Mariely = Mar Coronel (Marieli Coronel)? Confirmar y consolidar.
A13: Mamá Tejona | B13: Familia / Lifestyle / Box | C13: Familia & Kids, Sportswear, Alimentos, Wellness | D13: KATANA — Ecosistema Tejón | E13: 350000 | I13: Pendiente | J13: Ver Tarifario Maestro 2026 | K13: Tarifario construido con definición directa de Chuy. TikTok + réplica espejo en Reel se mantiene por encima del TikTok individual. Publicación fijada durante 7 días y exclusividad mensual se cotizan por separado. TikTok audio musical: pendiente de definir. Fuente: definición interna Chuy, 31-jul-2026. No incluye IVA, producción, viáticos, pauta ni derechos de uso adicionales.
A14: Tony Gastélum | B14: Calistenia / Fitness | C14: Sportswear, Fitness, Nutrición, Wellness, Tech deportiva | D14: KATANA — Casa | I14: Pendiente | J14: Ver Tarifario Maestro 2026 | K14: Rates altos; propuesto Viuda de Romero $4M | X14: PILOTO — FASE 1
A15: Mike Máquina del Mal | B15: Streamer / Fútbol | C15: Fútbol, Apuestas, Gaming, Streaming | D15: KATANA — Operable | H15: YouTube Live | Twitch | Kick | I15: Pendiente | J15: Ver Tarifario Maestro 2026 | K15: Deal Coca-Cola y X Gear cerrados; peleó Supernova. Tarifa top de la red
A16: Gambetiti | B16: Fútbol / Creator | C16: Fútbol, Apuestas, Bebidas | D16: KATANA — Operable | H16: @gambetiti | I16: Pendiente | J16: Ver Tarifario Maestro 2026 | K16: Deal Supernova y Mas Color Mundial cerrados
A17: Neux | B17: Gaming / Streaming | C17: Gaming, Tech, Telecom, Automotriz, Turismo | D17: KATANA — Operable | H17: @a_aguero19 / @neuxito | I17: Pendiente | J17: Ver Tarifario Maestro 2026 | K17: Bet Master always-on mensual; H2O Power
A18: Chuy Almada | B18: Fitness / Box | C18: Fitness, Box, Sportswear, Nutrición, Wellness, Combate | D18: KATANA — Chuy | H18: YouTube | I18: Pendiente | J18: Ver Tarifario Maestro 2026 | K18: PENDIENTE: completar bio, propuesta de valor, plataformas, métricas, assets, casos y restricciones. Categoría corregida por Jesús Gallardo el 2-ago-2026: fitness y box, no fútbol. | X18: PILOTO — FASE 1
A19: Yoiker | B19: Gaming / Streaming / Entretenimiento | C19: Gaming, Tech, Telecom, Eventos, Experiencias | D19: KATANA — Chuy | H19: Kick | I19: Pendiente | J19: Ver Tarifario Maestro 2026 | K19: No realiza streams. Sí realiza hosteo, con tarifa base desde $30,000 MXN. Escalera comercial validada: Reel IG $70,000; Post fijo IG $80,000; Reel Collab $85,000; TikTok + réplica espejo en Reel $140,000. Presencia en evento $60,000. TikTok audio musical pendiente de definir. Fuente: definición interna Chuy, 31-jul-2026.
A20: Kike Padilla / Rookie Leagues | B20: Béisbol / Streaming | C20: Béisbol, Gaming, Streaming, Tech, Eventos, Experiencias | D20: KATANA — Chuy | G20: 48.9K aprox. — validar | H20: Twitch | Kick | YouTube | I20: Pendiente | J20: Ver Tarifario Maestro 2026 | K20: Peleó preliminar Supernova 2025
A21: Stephany TV | B21: Gaming / Streaming / Entretenimiento | C21: Gaming, Tech, Telecom, Lifestyle, Eventos | D21: KATANA — Chuy | H21: Twitch / Kick — confirmar | I21: Pendiente | J21: Tarifario pendiente
A22: Padigol / Santiago Padilla | B22: Fútbol / Música | C22: Fútbol, Música, Bebidas, Streaming, Entretenimiento | D22: KATANA — Operable | H22: Podcast / Video | I22: Pendiente | J22: Ver Tarifario Maestro 2026 — histórico capturado, no vigente | K22: PILOTO — FASE 1. Tarifario histórico previo al Mundial capturado el 2-ago-2026. Incluye canales propios de Padigol y canales del Podcast de Padilla como inventarios separados. Falta incorporar Crónicas de Música y validar tarifas actuales antes de cotizar. | X22: PILOTO — FASE 1
A23: Edgar Cháirez | B23: MMA / UFC | C23: Bebidas, Apuestas, Sportswear, Fitness | D23: KATANA — Operable | I23: Pendiente | J23: Caso por caso — agregar al Tarifario Maestro
K24: Talento histórico de Chuy
K28: Deal Emergent AI cerrado
K29: Amazon: 3 campañas cerradas
K31: Tiene 350 mil seguidores. Reel IG actualizado a $50,000; Story a $15,000; la fijación se entiende específicamente como publicación fijada durante 7 días. No aplica masterclass. Puede venderse individualmente o como paquete familiar con Tejón; el paquete conjunto se cotiza caso por caso. Fuente: definición interna Chuy, 31-jul-2026. Pendiente aprobación de Ramiro.
K32: Actual campeón mundial de calistenia. Tarifas base comprobadas en Tabulador HONOR: TikTok $30,000; Reel IG $60,000; TikTok + Reel espejo $80,000; Story $25,000. El resto son propuestas internas aceptadas por Chuy y pendientes de aprobación de Ramiro. Reel Collab permanece pendiente para no confundirlo con TikTok + réplica espejo en Reel. Fuente: Tabulador HONOR + definición interna Chuy, 31-jul-2026. | V32: Colombia | W32: Por validar
K34: YouTube Live es su plataforma principal para streaming. Twitch y Kick quedan como plataformas disponibles sin tarifa automática; se cotizan caso por caso. Reel IG corregido a $50,000 MXN y Reel Collab a $60,000 MXN. Podcast: referencia mensual de $150,000 MXN, sujeta a formato, número de episodios e integración. Fuente: definición interna Chuy, 31-jul-2026. Propuesta interna pendiente de aprobación de Ramiro.
K36: HBO negociando 2 TikToks $180k
K38: Top podcast de fútbol; formato audio+video, cruce natural con Mar Coronel y patrocinios de apuestas
K41: Gaming y entretenimiento; opción para torneos, apariciones y experiencias. YouTube disponible: video dedicado, integración dentro de video y YouTube Short; tarifas pendientes de definir. Mantener como propuesta interna hasta aprobación. | L41: Pendiente | M41: Pendiente | N41: Pendiente | O41: Pendiente | P41: Pendiente | Q41: Pendiente | R41: Sin precio aprobado | S41: Por definir con Chuy | U41: Definir unitarios antes de ofrecer.
K42: Agregar al roster comercial de Chuy. YouTube es una de sus plataformas fuertes. No inventar tarifas; definir video dedicado, integración y Short antes de presentar. Fuente: definición interna Chuy, 31-jul-2026. Pendiente aprobación interna. | L42: Pendiente | M42: Pendiente | N42: Pendiente | O42: Pendiente | P42: Pendiente | Q42: Pendiente | R42: Sin precio aprobado | S42: Por definir con Chuy | U42: Definir categoría y handles al validar.
K43: Kick es su plataforma principal de streaming. Tarifas base de contenido tomadas del tabulador HONOR; complementos definidos internamente por Chuy. Pendiente aprobación de Ramiro. | L43: Pendiente | M43: Pendiente | N43: Pendiente | O43: Pendiente | P43: Pendiente | Q43: Pendiente | R43: Sin precio aprobado | S43: Por definir con Chuy | U43: Definir categoría y handles al validar.
K44: Se mantiene en el roster comercial de Chuy. Tiene inventario potencial en Twitch y/o Kick; confirmar plataforma principal, formatos y tarifas antes de presentar a cliente. No inventar precios. Fuente: instrucción interna Chuy, 31-jul-2026. | L44: Pendiente | M44: Pendiente | N44: Pendiente | O44: Pendiente | P44: Pendiente | Q44: Pendiente | R44: Sin precio aprobado | S44: Por definir con Chuy | U44: Más viáticos internacionales cuando aplique. | V44: Colombia | W44: Por validar
K45: Talento operable en Honduras; sujeto a validación de métricas y relación. | L45: Pendiente | M45: Pendiente | N45: Pendiente | O45: Pendiente | P45: Pendiente | Q45: Pendiente | R45: Sin precio aprobado | S45: Por definir con Chuy | U45: Más viáticos internacionales cuando aplique. | V45: Honduras | W45: Por validar
K46: Talento operable en Costa Rica; sujeto a validación de métricas y relación. | L46: Pendiente | M46: Pendiente | N46: Pendiente | O46: Pendiente | P46: Pendiente | Q46: Pendiente | R46: Sin precio aprobado | S46: Por definir con Chuy | U46: Más viáticos internacionales cuando aplique. | V46: Costa Rica | W46: Por validar
K47: Talento operable en Panamá; sujeto a validación de métricas y relación. | L47: Pendiente | M47: Pendiente | N47: Pendiente | O47: Pendiente | P47: Pendiente | Q47: Pendiente | R47: Sin precio aprobado | S47: Por definir con Chuy | U47: Más viáticos internacionales cuando aplique. | V47: Panamá | W47: Por validar
K48: Perfil operable para viajes, pareja, lifestyle y experiencias de destino. | L48: Pendiente | M48: Pendiente | N48: Pendiente | O48: Pendiente | P48: Pendiente | Q48: Pendiente | R48: Sin precio aprobado | S48: Por definir con Chuy | U48: Definir tarifas unitarias y paquete con Diana por separado. | V48: México | Y48: Por validar
K49: Perfil individual y participación posible en dupla con Chuy Alma. | M49: Pendiente | N49: Pendiente | O49: Pendiente | P49: Pendiente | Q49: Pendiente | R49: Sin precio aprobado | S49: Por definir con Chuy | U49: Definir tarifas individuales y precio especial en dupla. | Y49: Por validar
K50: Perfil operable para contenido de viaje, lifestyle y experiencias. | L50: 40000 | M50: 30000 | N50: Pendiente | O50: 15000 | P50: Pendiente | Q50: Pendiente | R50: Referencia histórica / validar | S50: CRM KIF histórico · julio 2026 | T50: Ramiro | U50: Referencia histórica: TikTok 40k, Reel 30k, Story 15k. Presencia histórica 25k. No usar sin validar vigencia. | V50: México | Y50: Por validar
K51: Manejar como una sola unidad comercial Kike Padilla / Rookie Leagues por ahora. YouTube y activación ajustados a una base más accesible. Plataformas secundarias disponibles; cotización específica según formato. Fuente: definición interna Chuy, 31-jul-2026.

Sheet TALENTOS_BACKUP_2026-08-01
A1: Talento | B1: Categoría | C1: Verticales que abre | D1: Tipo (casa / aliado) | E1: IG seguidores | F1: TikTok seguidores | G1: YouTube subs | H1: Otras plataformas | I1: Media kit HTML | J1: Tarifa base referencia (MXN) | K1: Notas / ángulo comercial | V1: País / mercado | W1: Estatus network | X1: Prioridad comercial | Y1: Disponibilidad
A2: Divino Espinoza | B2: Box — Campeón del mundo | C2: Bebidas, Apuestas, Sportswear, Streaming (historia sin contar) | D2: KATANA — Casa | I2: Pendiente | J2: Caso por caso | Presencia de marca en short de pelea: $750,000 MXN por combate | K2: Activo premium de box. La cifra de $750,000 MXN aplica como referencia para presencia de marca en el short durante el combate. Puede ampliarse a ropa de entrenamiento, llegada, pesaje, conferencia o contenido asociado según el paquete. Sujeto a evento, rival, transmisión, ubicación del logo, derechos, exclusividad y aprobación final. Fuente: definición interna Chuy, 31-jul-2026. Pendiente aprobación de Ramiro.
A3: Lazy Boy | B3: MMA / UFC — Mediático | C3: Bebidas, Apuestas, Sportswear, Grooming | D3: KATANA — Aliado (definir) | I3: Pendiente | J3: Caso por caso | K3: Atleta de alto rendimiento. Contenido digital, presencia en eventos, patrocinios deportivos, campamento, ropa y activaciones se cotizan caso por caso según marca, alcance, evento, derechos, exclusividad y disponibilidad. Fuente: definición interna Chuy, 31-jul-2026. Pendiente aprobación de Ramiro.
A4: Luis Pride | B4: MMA | C4: Bebidas, Apuestas, Sportswear, Nutrición | D4: KATANA — Casa | I4: Pendiente | J4: TikTok 150,000 | Reel IG 130,000 | TikTok + réplica espejo en Reel 225,000 | Reel Collab 180,000 | Post fijo IG 100,000 | Story 40,000 | Fijación 7 días 20,000 | Presencia 120,000 | Exclusividad mensual 50,000 | Stream 75,000 | Podcast N/A | Masterclass/experiencia 150,000 | Fee base por pelear 450,000 | TikTok audio musical pendiente | K4: Regla de espejo aplicada: 1.5x el precio más alto entre TikTok y Reel IG. Fee base por pelear: $450,000 MXN. Fuente: definición interna Chuy, 31-jul-2026.
A5: Ronny | B5: Box | C5: Bebidas, Apuestas, Sportswear, Nutrición | D5: KATANA — Casa | I5: Twitch | J5: TikTok 90,000 | Reel IG 130,000 | Reel Collab 150,000 | Post fijo IG 80,000 | Story 40,000 | Publicación fijada durante 7 días 15,000 | Presencia 100,000 | Exclusividad mensual 40,000 | Stream en Twitch 50,000 | Podcast N/A | Masterclass/experiencia 150,000 | Fee base por pelear 250,000 | K5: Streamer también activo en Twitch. La tarifa de stream registrada corresponde a Twitch. Fee base por pelear: $250,000 MXN. Fuente: Tabulador HONOR + ajustes internos de Chuy, 31-jul-2026. Propuesta interna pendiente de aprobación de Ramiro.
A6: Tejón de la Miel | B6: Box — Promesa (12 años) | C6: Familia & Kids, Sportswear, Alimentos | D6: KATANA — Casa | I6: Pendiente | J6: TikTok 100,000 | Reel IG 150,000 | Reel Collab 180,000 | Post fijo IG 80,000 | Story 40,000 | Fijación 7 días 15,000 | Presencia 100,000 | Exclusividad mensual 40,000 | Stream 50,000 | Podcast N/A | Masterclass/experiencia 150,000 | Peleas desde 50,000 | K6: TikTok igual a Mariel Estrella. Reel IG corregido a $150,000 y Reel Collab a $180,000. Peleas desde $50,000 MXN, sujeto a rival, evento, transmisión, ciudad, viáticos, exposición de marca y condiciones deportivas. Menor de edad: requiere autorización de tutor, revisión legal y aprobación interna. Fuente: definición interna Chuy, 31-jul-2026. Pendiente aprobación de Ramiro.
A7: César de la Parra | B7: Chef — Alto perfil | C7: Alimentos & Gastro, Bebidas, Electrodomésticos, Delivery, Turismo | D7: KATANA — Acceso exclusivo | I7: Pendiente | J7: Caso por caso | K7: Perfil altamente selectivo. Solo considerar marcas con afinidad real y aprobación expresa del talento. Priorizar acuerdos anuales, embajadurías de largo plazo o proyectos extraordinarios con alto valor creativo, gastronómico o reputacional. No manejar tarifario estándar ni cotizar por pieza aislada salvo excepción estratégica. Fuente: definición interna Chuy, 31-jul-2026. Requiere revisión de Jesús y Ramiro antes de presentar.
A8: Mar Coronel | B8: Fútbol — Up & coming / Tipster | C8: Apuestas & Fantasy, Financiero, Snacks, Telcos | D8: KATANA — Casa | I8: Pendiente | K8: Especializada en pronósticos/tips. Perfil ideal casas de apuestas.
A9: Nene Creative | B9: Gaming — #1 Rocket League | C9: Gaming, Tech & Telecom, Automotriz, Energy | D9: KATANA — Casa | I9: Twitch | YouTube | J9: TikTok 70,000 | Reel IG 40,000 | Reel Collab 35,000 | Post fijo IG 30,000 | Story 15,000 | Publicación fijada durante 7 días 10,000 | Presencia en evento 80,000 | Exclusividad mensual 25,000 | Stream en Twitch para evento 60,000 | Stream dedicado en Twitch para marca 120,000 por hora | Integración de marca en stream caso por caso | Podcast N/A | Masterclass/experiencia 100,000 | YouTube pendiente | K9: Twitch es su plataforma principal de streaming. Stream dedicado para marca: $120,000 MXN por hora. Integraciones dentro de streams existentes se cotizan caso por caso. YouTube disponible: video dedicado, integración y Short; tarifas pendientes. Fuente: definición interna Chuy, 31-jul-2026. Pendiente aprobación de Ramiro.
A10: Julio Orozco | B10: Música | C10: Bebidas, Festivales, Ticketing, Moda, Nightlife | D10: KATANA — Casa | I10: Kick | YouTube | J10: TikTok 30,000 | Reel IG 70,000 | Reel Collab 100,000 | Post fijo IG 50,000 | Story 30,000 | Publicación fijada durante 7 días 20,000 | Hosteo 80,000 | Stream en Kick para evento 50,000 | Podcast mensual 150,000 por 4 capítulos | Masterclass N/A | Exclusividad mensual 60,000 | YouTube pendiente | K10: Kick es su plataforma principal de streaming. YouTube disponible: video dedicado, integración dentro de video y Short; tarifas pendientes. Fuente: definición interna Chuy, 31-jul-2026. Propuesta interna pendiente de aprobación de Ramiro.
A11: Mariel Estrella | B11: Fitness / Lifestyle — Up & coming | C11: Belleza & Wellness, Sportswear, Apps, Healthy food | D11: KATANA — Casa | I11: Pendiente | K11: Cierres en curso — empujar.
A12: Mariely | B12: Fútbol | C12: Apuestas, Bebidas, Snacks, Telcos | D12: KATANA — Casa | I12: Pendiente | K12: POSIBLE DUPLICADO: ¿Mariely = Mar Coronel (Marieli Coronel)? Confirmar y consolidar.
A13: Juan de Dios G | B13: Storytime/Vlogging — Macro | C13: Entretenimiento, Bebidas, Apps | D13: KIF (red comercial) | H13: @juanddiosg | I13: Pendiente | J13: TikTok 200,000 | Reel IG 160,000 | TikTok + réplica espejo en Reel 240,000 | Post fijo IG 100,000 | Story 60,000 | Publicación fijada durante 7 días 25,000 | Presencia en evento 150,000 | Exclusividad mensual 75,000 | Promoción de audio musical en TikTok pendiente | K13: Tarifario construido con definición directa de Chuy. TikTok + réplica espejo en Reel se mantiene por encima del TikTok individual. Publicación fijada durante 7 días y exclusividad mensual se cotizan por separado. TikTok audio musical: pendiente de definir. Fuente: definición interna Chuy, 31-jul-2026. No incluye IVA, producción, viáticos, pauta ni derechos de uso adicionales.
A14: Javetas | B14: Fútbol/Vlogging — Macro | C14: Fútbol, Apuestas, Bebidas | D14: KIF (red comercial) | H14: @javetasenelarco | I14: Pendiente | K14: Rates altos; propuesto Viuda de Romero $4M
A15: Mercedes Roa | B15: Fútbol — Macro top | C15: Fútbol, Bebidas, Sportswear | D15: KIF (red comercial) | H15: @mercedes_roa | I15: Pendiente | K15: Deal Coca-Cola y X Gear cerrados; peleó Supernova. Tarifa top de la red
A16: Yoz Gless | B16: Fútbol femenil | C16: Fútbol, Apuestas | D16: KIF (red comercial) | H16: @yoz_gless_ | I16: Pendiente | K16: Deal Supernova y Mas Color Mundial cerrados
A17: Nikkole Teja | B17: Fútbol femenil | C17: Fútbol, Apuestas, Bebidas | D17: KIF (red comercial) | H17: @nikkoleteja_ | I17: Pendiente | K17: Bet Master always-on mensual; H2O Power
A18: Canelo Angulo | B18: Fútbol / ex-jugador | C18: Fútbol, Apuestas (tipster) | D18: KIF (red comercial) | H18: @jrangulo19 | I18: Pendiente | K18: Cliente TipsterPages y eBay; DT All Stars
A19: Gambetiti | B19: Fútbol-creator | C19: Fútbol, Apuestas, Bebidas | D19: KIF (red comercial) | H19: @gambetiti | I19: Pendiente | J19: TikTok 100,000 | Reel IG 70,000 | TikTok + réplica espejo en Reel 140,000 | Reel Collab 85,000 | Post fijo IG 80,000 | Story 25,000 | Publicación fijada durante 7 días 10,000 | Presencia en evento 60,000 | Hosteo desde 30,000 | Exclusividad mensual 30,000 | TikTok audio musical pendiente | Podcast N/A | Masterclass/experiencia N/A | Stream N/A | K19: No realiza streams. Sí realiza hosteo, con tarifa base desde $30,000 MXN. Escalera comercial validada: Reel IG $70,000; Post fijo IG $80,000; Reel Collab $85,000; TikTok + réplica espejo en Reel $140,000. Presencia en evento $60,000. TikTok audio musical pendiente de definir. Fuente: definición interna Chuy, 31-jul-2026.
A20: Ian Granados | B20: Fútbol-creator | C20: Fútbol, Familia | D20: KIF (red comercial) | H20: @ian.granados1 | I20: Pendiente | K20: Peleó preliminar Supernova 2025
A21: Mariana Grimaldi | B21: Comedy/Lifestyle — Macro | C21: Lifestyle, Bebidas, Beauty | D21: KIF (red comercial) | H21: @marianagrimaldi__ | I21: Pendiente
A22: Kozue | B22: Lifestyle/Entretenimiento — Macro | C22: Lifestyle, Tech | D22: KIF (red comercial) | H22: @kozuehayashii | I22: Pendiente
A23: Camila Sánchez | B23: TikTok/Lifestyle | C23: Lifestyle, Beauty | D23: KIF (red comercial) | H23: @camilasanchhez | I23: Pendiente
A24: Luisito Rey | B24: Comedy/Sketch | C24: Entretenimiento, Alimentos | D24: KIF (red comercial) | H24: @luisitorey | I24: Pendiente | K24: Talento histórico de Chuy
A25: Soy Mirrey Bro | B25: Luxury lifestyle — Macro | C25: Lifestyle, Bebidas premium | D25: KIF (red comercial) | H25: @soymirreybro | I25: Pendiente
A26: Edwin Mendoza | B26: Sports — Macro | C26: Fútbol, Sportswear | D26: KIF (red comercial) | H26: @edwinmendozza | I26: Pendiente
A27: Javier Rojo | B27: Sports/Gymnastics | C27: Fitness, Sportswear | D27: KIF (red comercial) | H27: @javierrojomx | I27: Pendiente
A28: Marurista | B28: Lifestyle — Macro | C28: Lifestyle, Tech | D28: KIF (red comercial) | H28: @marurista | I28: Pendiente | K28: Deal Emergent AI cerrado
A29: Ana Fer Lemus | B29: Lifestyle — Macro | C29: Lifestyle, E-commerce | D29: KIF (red comercial) | H29: @anafer.lemus | I29: Pendiente | K29: Amazon: 3 campañas cerradas
A30: Yetus Prime | B30: Entretenimiento — Macro | C30: Entretenimiento, Gaming | D30: KIF (red comercial) | H30: @yetus_prime | I30: Pendiente
A31: Mamá Tejona | B31: Familia / Lifestyle / Box | C31: Familia & Kids, Sportswear, Alimentos, Wellness | D31: KATANA — Ecosistema Tejón | E31: 350000 | I31: Pendiente | J31: TikTok 25,000 | Reel IG 50,000 | Reel Collab 40,000 | Post fijo IG 20,000 | Story 15,000 | Publicación fijada durante 7 días 5,000 | Presencia 15,000 | Exclusividad mensual 10,000 | Stream 15,000 | Podcast N/A | Masterclass/experiencia N/A | K31: Tiene 350 mil seguidores. Reel IG actualizado a $50,000; Story a $15,000; la fijación se entiende específicamente como publicación fijada durante 7 días. No aplica masterclass. Puede venderse individualmente o como paquete familiar con Tejón; el paquete conjunto se cotiza caso por caso. Fuente: definición interna Chuy, 31-jul-2026. Pendiente aprobación de Ramiro.
A32: Tony Gastélum | B32: Calistenia / Fitness — Campeón mundial vigente | C32: Sportswear, Fitness, Nutrición, Wellness, Tech deportiva | D32: KATANA — Casa | I32: Pendiente | J32: TikTok 30,000 | TikTok + réplica espejo en Reel 80,000 | Reel IG 60,000 | Reel Collab pendiente | Post fijo IG 40,000 | Story 25,000 | Publicación fijada durante 7 días 10,000 | Presencia en evento 50,000 | Exclusividad mensual 25,000 | Stream en evento 40,000 | Stream dedicado para marca 80,000 por hora | Integración de marca en stream caso por caso | Podcast N/A | Masterclass/experiencia 80,000 | K32: Actual campeón mundial de calistenia. Tarifas base comprobadas en Tabulador HONOR: TikTok $30,000; Reel IG $60,000; TikTok + Reel espejo $80,000; Story $25,000. El resto son propuestas internas aceptadas por Chuy y pendientes de aprobación de Ramiro. Reel Collab permanece pendiente para no confundirlo con TikTok + réplica espejo en Reel. Fuente: Tabulador HONOR + definición interna Chuy, 31-jul-2026. | V32: Colombia | W32: Por validar
A33: Ramón Villa | B33: Sports — Macro | C33: Fútbol, Sportswear | D33: KIF (red comercial) | H33: @ramonvillazg | I33: Pendiente
A34: Mike Máquina del Mal | B34: Streamer #1 Fútbol | C34: Fútbol, Apuestas, Gaming, Streaming — Fórmula S (host) | D34: KIF (red comercial) | H34: @mikemaquinadelmalshow | I34: YouTube Live | YouTube | Twitch | Kick | J34: TikTok 100,000 | Reel IG 50,000 | Reel Collab 60,000 | Post fijo IG 60,000 | Story 30,000 | Publicación fijada durante 7 días 15,000 | Presencia en evento 80,000 | Exclusividad mensual 40,000 | Stream dedicado en YouTube Live para marca 100,000 por hora | Integración dentro de live caso por caso | Podcast mensual 150,000 | Masterclass/experiencia 100,000 | Promoción de audio musical en TikTok pendiente | K34: YouTube Live es su plataforma principal para streaming. Twitch y Kick quedan como plataformas disponibles sin tarifa automática; se cotizan caso por caso. Reel IG corregido a $50,000 MXN y Reel Collab a $60,000 MXN. Podcast: referencia mensual de $150,000 MXN, sujeta a formato, número de episodios e integración. Fuente: definición interna Chuy, 31-jul-2026. Propuesta interna pendiente de aprobación de Ramiro.
A35: Espe Borras | B35: Sports | C35: Fútbol | D35: KIF (red comercial) | H35: @espe | I35: Pendiente
A36: Geryna Sotelo | B36: Sports | C36: Fútbol, Streaming | D36: KIF (red comercial) | H36: @GerynaSotelo | I36: Pendiente | K36: HBO negociando 2 TikToks $180k
A37: Los Futbolitos | B37: Sports/Podcast — Macro | C37: Fútbol, Snacks | D37: KIF (red comercial) | H37: @losfutbolitostv | I37: Pendiente
A38: Padigol | B38: Podcast — Top Podcast Fútbol | C38: Fútbol, Apuestas, Bebidas, Streaming | D38: KIF (red comercial) | I38: Pendiente | K38: Top podcast de fútbol; formato audio+video, cruce natural con Mar Coronel y patrocinios de apuestas
A41: Neux | B41: Gaming / Rocket League / Streaming | C41: Gaming, Tech, Telecom, Automotriz, Turismo | D41: KATANA — Operable | H41: @a_aguero19 / @neuxito | I41: Pendiente | K41: Gaming y entretenimiento; opción para torneos, apariciones y experiencias. YouTube disponible: video dedicado, integración dentro de video y YouTube Short; tarifas pendientes de definir. Mantener como propuesta interna hasta aprobación. | L41: Pendiente | M41: Pendiente | N41: Pendiente | O41: Pendiente | P41: Pendiente | Q41: Pendiente | R41: Sin precio aprobado | S41: Por definir con Chuy | U41: Definir unitarios antes de ofrecer.
A42: Chuy Almada | B42: YouTube / Entretenimiento / Lifestyle | C42: Entretenimiento, Lifestyle, Cultura, Marcas de consumo, Experiencias | D42: KATANA — Chuy | I42: Pendiente | J42: YouTube disponible: video dedicado | integración dentro de video | YouTube Short | Tarifas pendientes | K42: Agregar al roster comercial de Chuy. YouTube es una de sus plataformas fuertes. No inventar tarifas; definir video dedicado, integración y Short antes de presentar. Fuente: definición interna Chuy, 31-jul-2026. Pendiente aprobación interna. | L42: Pendiente | M42: Pendiente | N42: Pendiente | O42: Pendiente | P42: Pendiente | Q42: Pendiente | R42: Sin precio aprobado | S42: Por definir con Chuy | U42: Definir categoría y handles al validar.
A43: Yoiker | B43: Gaming / Streaming / Entretenimiento | C43: Gaming, Tech, Telecom, Eventos, Experiencias | D43: KATANA — Chuy | I43: Kick | J43: TikTok 25,000 | TikTok + réplica espejo en Reel 60,000 | Reel IG 40,000 | Reel Collab 35,000 | Post fijo IG 30,000 | Story 20,000 | Publicación fijada durante 7 días 10,000 | Presencia 50,000 | Exclusividad mensual 25,000 | Stream en Kick para evento 40,000 | Stream dedicado en Kick 70,000 por hora | Integración de marca en stream caso por caso | Podcast N/A | Masterclass/experiencia 100,000 | K43: Kick es su plataforma principal de streaming. Tarifas base de contenido tomadas del tabulador HONOR; complementos definidos internamente por Chuy. Pendiente aprobación de Ramiro. | L43: Pendiente | M43: Pendiente | N43: Pendiente | O43: Pendiente | P43: Pendiente | Q43: Pendiente | R43: Sin precio aprobado | S43: Por definir con Chuy | U43: Definir categoría y handles al validar.
A44: Stephany TV | B44: Gaming / Streaming / Entretenimiento | C44: Gaming, Tech, Telecom, Lifestyle, Eventos | D44: KATANA — Chuy | I44: Twitch / Kick — confirmar plataforma principal | J44: Tarifario pendiente | K44: Se mantiene en el roster comercial de Chuy. Tiene inventario potencial en Twitch y/o Kick; confirmar plataforma principal, formatos y tarifas antes de presentar a cliente. No inventar precios. Fuente: instrucción interna Chuy, 31-jul-2026. | L44: Pendiente | M44: Pendiente | N44: Pendiente | O44: Pendiente | P44: Pendiente | Q44: Pendiente | R44: Sin precio aprobado | S44: Por definir con Chuy | U44: Más viáticos internacionales cuando aplique. | V44: Colombia | W44: Por validar
A45: Supremo | B45: Creator / Entretenimiento | C45: Lifestyle, Entretenimiento, Turismo, Bebidas | D45: KATANA — Network extranjero | H45: Honduras | I45: Pendiente | K45: Talento operable en Honduras; sujeto a validación de métricas y relación. | L45: Pendiente | M45: Pendiente | N45: Pendiente | O45: Pendiente | P45: Pendiente | Q45: Pendiente | R45: Sin precio aprobado | S45: Por definir con Chuy | U45: Más viáticos internacionales cuando aplique. | V45: Honduras | W45: Por validar
A46: Keizy | B46: Creator / Entretenimiento | C46: Lifestyle, Entretenimiento, Turismo, Bebidas | D46: KATANA — Network extranjero | H46: Costa Rica | I46: Pendiente | K46: Talento operable en Costa Rica; sujeto a validación de métricas y relación. | L46: Pendiente | M46: Pendiente | N46: Pendiente | O46: Pendiente | P46: Pendiente | Q46: Pendiente | R46: Sin precio aprobado | S46: Por definir con Chuy | U46: Más viáticos internacionales cuando aplique. | V46: Costa Rica | W46: Por validar
A47: Rafe Lucado | B47: Creator / Entretenimiento | C47: Lifestyle, Entretenimiento, Turismo, Bebidas | D47: KATANA — Network extranjero | H47: Panamá | I47: Pendiente | K47: Talento operable en Panamá; sujeto a validación de métricas y relación. | L47: Pendiente | M47: Pendiente | N47: Pendiente | O47: Pendiente | P47: Pendiente | Q47: Pendiente | R47: Sin precio aprobado | S47: Por definir con Chuy | U47: Más viáticos internacionales cuando aplique. | V47: Panamá | W47: Por validar
A48: Chuy Alma | B48: Lifestyle / Pareja / Entretenimiento | C48: Turismo, Hotelería, Gastronomía, Lifestyle, Experiencias | D48: KATANA — Operable | I48: Pendiente | K48: Perfil operable para viajes, pareja, lifestyle y experiencias de destino. | L48: Pendiente | M48: Pendiente | N48: Pendiente | O48: Pendiente | P48: Pendiente | Q48: Pendiente | R48: Sin precio aprobado | S48: Por definir con Chuy | U48: Definir tarifas unitarias y paquete con Diana por separado. | V48: México | Y48: Por validar
A49: Diana | B49: Lifestyle / Pareja / Bienestar | C49: Turismo, Hotelería, Wellness, Gastronomía, Experiencias | D49: KATANA — Operable | I49: Pendiente | K49: Perfil individual y participación posible en dupla con Chuy Alma. | L49: Pendiente | M49: Pendiente | N49: Pendiente | O49: Pendiente | P49: Pendiente | Q49: Pendiente | R49: Sin precio aprobado | S49: Por definir con Chuy | U49: Definir tarifas individuales y precio especial en dupla. | V49: México | Y49: Por validar
A50: Diego Alamillo | B50: Lifestyle / Entretenimiento | C50: Lifestyle, Turismo, Entretenimiento, Bebidas, Tech | D50: KATANA — Operable | I50: Pendiente | K50: Perfil operable para contenido de viaje, lifestyle y experiencias. | L50: 40000 | M50: 30000 | N50: Pendiente | O50: 15000 | P50: Pendiente | Q50: Pendiente | R50: Referencia histórica / validar | S50: CRM KIF histórico · julio 2026 | T50: Ramiro | U50: Referencia histórica: TikTok 40k, Reel 30k, Story 15k. Presencia histórica 25k. No usar sin validar vigencia. | V50: México | Y50: Por validar
A51: Kike Padilla / Rookie Leagues | B51: Béisbol / Streaming / Experiencias deportivas | C51: Béisbol, Gaming, Streaming, Tech, Eventos, Experiencias | D51: KATANA — Chuy | G51: 48.9K aprox. — validar | H51: Twitch | Kick | YouTube | I51: Pendiente | J51: TikTok 30,000 | Reel IG 40,000 | TikTok + réplica espejo en Reel 60,000 | Reel Collab 50,000 | Post fijo IG 30,000 | Story 15,000 | Publicación fijada durante 7 días 10,000 | Presencia/hosteo 60,000 | Stream para evento 50,000 | Stream dedicado para marca 60,000 por hora | Integración de marca en stream caso por caso | Video dedicado YouTube 40,000 | Integración YouTube 25,000 | YouTube Short 20,000 | Activación/experiencia de béisbol 60,000 | Exclusividad mensual 30,000 | TikTok audio musical pendiente | K51: Manejar como una sola unidad comercial Kike Padilla / Rookie Leagues por ahora. YouTube y activación ajustados a una base más accesible. Plataformas secundarias disponibles; cotización específica según formato. Fuente: definición interna Chuy, 31-jul-2026.

Sheet MARCAS TARGET
A1: SEÑALÉTICA: | B1: ACTIVO — ya hay contacto real / cerrado | C1: A UN PASO — contrato / por firmar | D1: EN PROCESO — negociación / propuesta / tibio | E1: FRÍO — target, aún sin contactar | F1: PERDIDO / DORMIDO — reactivar o descartar
A2: Vertical | B2: Marca | C2: ¿Relación previa? | D2: Por qué es target | E2: Talento que le pega | F2: Agencia que la maneja (si se sabe) | G2: Decision-maker (nombre) | H2: Cargo | I2: Fuente del dato | J2: Pasado a LEADS
A3: Bebidas | B3: Cerveza Victoria | C3: Sí - pasada | D3: Ya ha invertido con nosotros | E3: Pool Combate (paquete) | I3: Relación Chuy | J3: No
A4: Tech & Telecom | B4: Honor | C4: Sí - pasada | D4: Ya ha invertido con nosotros; gasta fuerte en creators MX | E4: Nene Creative | I4: Relación Chuy | J4: No
A5: Apuestas & Fantasy | B5: Caliente | C5: Sí - activa | D5: Líder local; sin programa público de afiliados — entra por relación || Gambetiti CERRADO por firmar; Rivaldios 3 historias/mes; Luis Pride propuesta enviada. Contacto: Pony | E5: Mar Coronel | I5: Scouting Claude | J5: No
A6: Apuestas & Fantasy | B6: Betano | C6: No | D6: Crecimiento fuerte en la región, patrocinios Liga MX | E6: Pool Combate (paquete) | I6: Scouting Claude | J6: No
A7: Apuestas & Fantasy | B7: Playdoit | C7: No | D7: Mencionada por Chuy como target | E7: Mar Coronel | I7: Chuy | J7: No
A8: Streaming & Entretenimiento | B8: Netflix | C8: Sí - pasada | D8: Bahía Colorada #1 — historial con contenido | E8: Varios / Pool mixto | I8: Relación Chuy | J8: No
A9: Streaming & Entretenimiento | B9: Paramount | C9: No | D9: Mencionada por Chuy | E9: Varios / Pool mixto | I9: Chuy | J9: No
A10: Streaming & Entretenimiento | B10: Kick | C10: Sí - pasada | D10: Broadcast Fórmula S | E10: Varios / Pool mixto | I10: Relación | J10: No
A11: Bebidas | B11: Grupo Modelo (corporativo) | C11: No | D11: Mayor anunciante cervecero MX; estrategia basada en creators, eventos masivos y cultura | E11: Pool Combate (paquete) | G11: Felipe Ambra | H11: VP de Marketing | I11: Forbes MX, may 2026 | J11: No
A12: Bebidas | B12: Cerveza Victoria | C12: Sí - pasada | D12: Ya invirtió con nosotros; marca top-6 más valiosa de MX (Kantar BrandZ) | E12: Pool Combate (paquete) | G12: Gabriel Díaz | H12: Director de Cerveza Victoria | I12: Produ/Kantar, mar 2025 — confirmar en LinkedIn | J12: No
A13: Bebidas | B13: Corona | C13: No | D13: Marca #1 más valiosa de MX; plataformas de música, deporte y entretenimiento | E13: Varios / Pool mixto | G13: Marcela Treviño / Yune Aranguren | H13: Directora de Corona / Directora Marcas Core (Corona y Victoria) | I13: Produ/Kantar, mar 2025 — confirmar en LinkedIn | J13: No
A14: Bebidas | B14: Cerveza Modelo | C14: No | D14: Top-3 marca más valiosa MX | E14: Pool Combate (paquete) | G14: César Alcántara | H14: Director de Cerveza Modelo | I14: Produ/Kantar, mar 2025 — confirmar en LinkedIn | J14: No
A15: Bebidas | B15: Grupo Modelo — Marcas Premium | C15: No | D15: Pacífico, premium portfolio | E15: Julio Orozco | G15: Mariana Cuellar | H15: Directora de Marcas Premium | I15: Produ/Kantar, mar 2025 — confirmar en LinkedIn | J15: No
A16: Bebidas | B16: HEINEKEN México (corporativo) | C16: No | D16: Tecate, Indio, Dos Equis, Bohemia; campañas digitales con influencers (Tecate 0.0: 106 piezas, 99% audiencia digital) | E16: Pool Combate (paquete) | F16: LePub Mexico City (creativa de Tecate) | G16: Marta García | H16: VP de Marketing | I16: Comunicado Heineken MX ~2024 — confirmar en LinkedIn | J16: No
A17: Bebidas | B17: HEINEKEN — Marcas Premium | C17: No | D17: Heineken, Amstel Ultra (activaciones deporte: pádel, F1) | E17: Mariel Estrella | G17: Karla Patricia González Álvarez | H17: Directora de Marcas Premium | I17: Milenio, dic 2024 — confirmar en LinkedIn | J17: No
A18: Bebidas | B18: HEINEKEN — Media | C18: No | D18: Decide inversión en medios y digital de todo el portafolio | E18: Varios / Pool mixto | G18: Pablo Alfredo Rada | H18: Director de Media & CDAU | I18: Milenio, dic 2024 — confirmar en LinkedIn | J18: No
A19: Bebidas | B19: Tecate | C19: No | D19: Marca más premiada de MX en Clio 2026; festival Pa'l Norte; combate/box es territorio histórico de Tecate | E19: Pool Combate (paquete) | F19: LePub Mexico City | I19: Merca 2.0, abr 2026 | J19: No
A20: Bebidas | B20: Indio | C20: No | D20: Campañas de barrio/cultura urbana (Tanderos, Mexologia) | E20: Julio Orozco | I20: Prensa Heineken 2025 | J20: No
A21: Tech & Telecom | B21: Honor México | C21: Sí - activa | D21: Ya invirtió con nosotros; muy activa en marketing MX || Deal en proceso con Rivaldios (contacto: Francisco); histórico con Katana | E21: Nene Creative | G21: Julio Meneses | H21: CMO / Director de Marketing México | I21: LinkedIn + Isopixel — confirmar vigencia | J21: No
A22: Tech & Telecom | B22: Honor Latam | C22: No | D22: Capa regional que aprueba presupuestos grandes | E22: Nene Creative | G22: Jesús Quintero | H22: Head de Marketing Latinoamérica | I22: El Financiero, oct 2024 — confirmar en LinkedIn | J22: No
A23: Tech & Telecom | B23: Telcel | C23: Sí - pasada | D23: COMPROBADO: patrocinó Supernova Strikers 2025 (10M+ viewers). Compra creator boxing MX || Propuesta anual CPA $3.25M enviada (31 talentos, modelo costo por acción) | E23: Pool Combate (paquete) | I23: Merca 2.0, ago 2025 | J23: No
A24: Alimentos & Gastro | B24: Farmacias Similares | C24: No | D24: COMPROBADO: patrocinó Supernova Strikers 2025 | E24: Varios / Pool mixto | I24: Merca 2.0, ago 2025 | J24: No
A25: Streaming & Entretenimiento | B25: DAZN | C25: No | D25: COMPROBADO: transmitió Supernova; plataforma global de combate. Target para derechos FIERA | E25: Pool Combate (paquete) | I25: Merca 2.0, ago 2025 | J25: No
A26: Streaming & Entretenimiento | B26: Podimo | C26: No | D26: COMPROBADO: patrocinó Supernova Strikers 2025; compra audio/creators | E26: Julio Orozco | I26: Merca 2.0, ago 2025 | J26: No
A27: Alimentos & Gastro | B27: Domino's Pizza | C27: No | D27: COMPROBADO: patrocinó Supernova 2025; cliente de BrandMe | E27: Varios / Pool mixto | F27: BrandMe (influencer mkt) | I27: Merca 2.0, ago 2025 | J27: No
A28: Alimentos & Gastro | B28: McCormick | C28: No | D28: COMPROBADO: patrocinó Supernova 2025 Y repite en Génesis 2026. Fit natural con César (chef) | E28: César de la Parra | I28: Merca 2.0 + El Financiero | J28: No
A29: Streaming & Entretenimiento | B29: Cinépolis | C29: No | D29: COMPROBADO: patrocinó y transmitió Supernova en salas | E29: Varios / Pool mixto | I29: Merca 2.0, ago 2025 | J29: No
A30: Alimentos & Gastro | B30: Sabritas (PepsiCo) | C30: No | D30: COMPROBADO: zona patrocinada Supernova Génesis 2026 | E30: Pool Combate (paquete) | I30: El Financiero, dic 2025 | J30: No
A31: Financiero & Fintech | B31: Elektra / Banco Azteca | C31: No | D31: COMPROBADO: zonas patrocinadas Supernova Génesis 2026. Banca popular compra creators | E31: Varios / Pool mixto | I31: El Financiero, dic 2025 | J31: No
A32: Familia & Kids | B32: Mercado Libre | C32: No | D32: COMPROBADO: zona patrocinada Supernova Génesis 2026; mayor anunciante e-commerce | E32: Varios / Pool mixto | I32: El Financiero, dic 2025 | J32: No
A33: Familia & Kids | B33: Miniso | C33: No | D33: COMPROBADO: zona patrocinada Supernova Génesis 2026; audiencia joven/familiar | E33: Tejón + Mamá (dupla familiar) | I33: El Financiero, dic 2025 | J33: No
A34: Bebidas | B34: Pepsi | C34: No | D34: COMPROBADO: zona patrocinada Supernova Génesis 2026 | E34: Pool Combate (paquete) | I34: El Financiero, dic 2025 | J34: No
A35: Tech & Telecom | B35: Toyota | C35: No | D35: COMPROBADO: zona patrocinada Supernova Génesis 2026. Automotriz+gaming: fit Nene (Rocket League=coches) | E35: Nene Creative | I35: El Financiero, dic 2025 | J35: No
A36: Tech & Telecom | B36: Mega (Megacable) | C36: No | D36: COMPROBADO: zona patrocinada Supernova Génesis 2026 | E36: Varios / Pool mixto | I36: El Financiero, dic 2025 | J36: No
A37: Bebidas | B37: Boing (Pascual) | C37: No | D37: COMPROBADO: zona patrocinada Supernova Génesis 2026 | E37: Tejón + Mamá (dupla familiar) | I37: El Financiero, dic 2025 | J37: No
A38: Bebidas | B38: Tecate (box) | C38: No | D38: DUEÑO histórico del territorio box MX: patrocina Canelo y box profesional ("Te hace falta ver más bax") | E38: Divino Espinoza | F38: LePub Mexico City | I38: InformaBTL + historial marca | J38: No
A39: Sportswear & Nutrición | B39: Under Armour | C39: No | D39: COMPROBADO: patrocina Canelo desde 2012; deportes de contacto es su territorio | E39: Divino Espinoza | I39: Radio Fórmula, 2024 | J39: No
A40: Sportswear & Nutrición | B40: Everlast | C40: No | D40: COMPROBADO: patrocina Canelo; marca endémica de box, entrada natural para todo el pool | E40: Pool Combate (paquete) | I40: Revista Clase, 2021 | J40: No
A41: Financiero & Fintech | B41: Value Grupo Financiero | C41: No | D41: COMPROBADO: patrocinador histórico de Canelo (calzoncillo en peleas) | E41: Divino Espinoza | I41: El Universal/Clase, 2019-24 | J41: No
A42: Financiero & Fintech | B42: Broxel | C42: No | D42: COMPROBADO: fintech mexicana patrocinadora de Canelo | E42: Divino Espinoza | I42: El Informador, may 2024 | J42: No
A43: Sportswear & Nutrición | B43: Gatorade | C43: No | D43: COMPROBADO: patrocinó peleas de Canelo; hidratación deportiva compra box | E43: Pool Combate (paquete) | I43: Record, 2022 | J43: No
A44: Sportswear & Nutrición | B44: Yaoca | C44: No | D44: COMPROBADO: bebida hidratante mexicana que patrocina a Canelo; marca emergente accesible | E44: Mar Coronel | I44: Radio Fórmula, 2023 | J44: No
A45: Financiero & Fintech | B45: Revolut / neobancos MX (Nu, Klar, Stori) | C45: No | D45: PATRÓN Velada V: fintech es patrocinador principal del formato. En MX: Nu, Klar, Stori compran creators | E45: Varios / Pool mixto | I45: Marketing4ecommerce, jul 2025 | J45: No
A46: Belleza & Wellness | B46: CeraVe (L'Oréal) | C46: No | D46: PATRÓN Velada V: skincare activó IN-RING (luchador CeraVestia). Grooming+combate funciona | E46: Pool Combate (paquete) | I46: Ecommerce News, jul 2025 | J46: No
A47: Alimentos & Gastro | B47: Grefusa / snacks (Barcel, Sabritas) | C47: No | D47: PATRÓN Velada: snacks es patrocinador veterano del formato en 5 ediciones | E47: Pool Combate (paquete) | I47: Ecommerce News, jul 2025 | J47: No
A48: Tech & Telecom | B48: Nothing / G-Shock (Casio) | C48: No | D48: PATRÓN Velada V: smartphones retadores y relojes compran creator boxing | E48: Pool Combate (paquete) | I48: Marketing4ecommerce, jul 2025 | J48: No
A49: Streaming & Entretenimiento | B49: Spotify | C49: No | D49: PATRÓN Velada V: banda sonora oficial + playlists de peleadores. Fit Julio (música) + FIERA | E49: Julio Orozco | I49: A Creative, jul 2025 | J49: No
A50: Financiero & Fintech | B50: Banorte | C50: No | D50: COMPROBADO: patrocinador Selección MX + naming Estadio Banorte. Máximo gasto en deporte | E50: Mariely | I50: Expansión, jun 2026 | J50: No
... A52: Apuestas & Fantasy | B52: Caliente (fútbol) | C52: Sí - activa | D52: COMPROBADO: patrocina Selección, varios clubes Liga MX y medios deportivos. Máximo actor betting-deporte || Misma cuenta activa (Pony) — consolidar con Caliente | E52: Mar Coronel | I52: Expansión, jun 2026 | J52: No
A53: Familia & Kids | B53: Amazon México | C53: Sí - activa | D53: COMPROBADO: patrocinador Selección + Liga MX + Femenil desde mar 2025 (100M aficionados) || 3 campañas cerradas con Ana Fer Lemus vía agencia VKNG | E53: Varios / Pool mixto | G53: Pedro Huerta (Country Manager, da contexto) | H53: Country Manager | I53: Milenio, mar 2025 | J53: No
A54: Bebidas | B54: Coca-Cola México | C54: Sí - activa | D54: COMPROBADO: patrocinador histórico Selección MX; también patrocinó La Velada V || Deal CERRADO con Mercedes Roa (contacto: Mon Hernández) | E54: Varios / Pool mixto | I54: Milenio, jun 2026 | J54: No
A55: Sportswear & Nutrición | B55: adidas México | C55: No | D55: COMPROBADO: patrocinador técnico Selección MX; dueño del fútbol MX | E55: Mariely | I55: Milenio, jun 2026 | J55: No
A56: Belleza & Wellness | B56: Grupo Grisi | C56: No | D56: COMPROBADO: patrocinador Selección MX rumbo al Mundial | E56: Mariel Estrella | I56: Milenio, jun 2026 | J56: No
A57: Tech & Telecom | B57: Hyundai México | C57: No | D57: COMPROBADO: patrocinador Mundial; CEO reporta conversión directa en ventas | E57: Varios / Pool mixto | G57: Edgar Carranza (CEO, contexto) | H57: CEO | I57: Milenio, jun 2026 | J57: No
A58: Alimentos & Gastro | B58: Maggi (Nestlé) | C58: No | D58: COMPROBADO: patrocinador oficial Liga MX + Selección hasta dic 2026; mayor inversión de su historia en MX. Fit natural César (cocina) | E58: César de la Parra | G58: Mario López | H58: Group Marketing Manager Culinarios, Nestlé | I58: Nestlé/La Silla Rota, abr 2025 | J58: No
A59: Alimentos & Gastro | B59: Little Caesars | C59: No | D59: COMPROBADO: patrocinador Selección (mayor, menores, femenil) | E59: Tejón + Mamá (dupla familiar) | G59: Roberto Guzmán | H59: Director de Mercadotecnia | I59: Mediotiempo, feb 2024 — confirmar en LinkedIn | J59: No
A60: Streaming & Entretenimiento | B60: Paramount+ / Paramount | C60: Sí - activa | D60: CONTACTO DIRECTO de Chuy. Compra contenido y talento; target derechos y co-producción FIERA | E60: Varios / Pool mixto | G60: (contacto de Chuy) | I60: Relación Chuy | J60: No
A61: Streaming & Entretenimiento | B61: ESPN / Disney+ | C61: Sí - activa | D61: CONTACTO DIRECTO. Historial: All Stars MX en Disney+/ESPN (160K concurrentes) + broadcast Fórmula S | E61: Varios / Pool mixto | G61: (contacto de Chuy) | I61: Relación Chuy | J61: No
A62: Streaming & Entretenimiento | B62: Max (HBO) | C62: Sí - activa | D62: Historial: Ugly #1 HBO. Target contenido/documental (ángulo Divino) || Negociando: Geryna Sotelo, 2 TikToks $180k (contacto: Sofía Hernández) | E62: Divino Espinoza | I62: Relación Chuy | J62: No
A63: Streaming & Entretenimiento | B63: Prime Video / Amazon Music | C63: No | D63: Amazon ya patrocina FMF/Liga MX; Prime compra deporte en vivo y música (Edén Muñoz exclusivo Amazon Music) | E63: Julio Orozco | I63: Milenio, mar 2025 | J63: No
A64: Streaming & Entretenimiento | B64: Twitch | C64: No | D64: Plataforma madre del formato velada (récord 9-10M concurrentes). Target partnership FIERA | E64: Pool Combate (paquete) | I64: Marketing4ecommerce, jul 2025 | J64: No
A65: Streaming & Entretenimiento | B65: TikTok | C65: Sí - pasada | D65: Broadcast Fórmula S; compra contenido en vivo LATAM | E65: Varios / Pool mixto | I65: Relación | J65: No
A66: Bebidas | B66: Red Bull México | C66: No | D66: Dueño global del territorio deporte extremo + gaming + creators; produce sus propios eventos | E66: Nene Creative | I66: Historial de marca | J66: No
A67: Bebidas | B67: Monster Energy | C67: No | D67: Patrocinador oficial de UFC (lona del octágono); compra MMA y combate a nivel global | E67: Lacy Way | I67: Historial de marca UFC | J67: No
A68: Gaming & Esports | B68: Rocket League / Epic Games | C68: No | D68: Nene es #1 en Rocket League: target de programa de creators y torneos oficiales | E68: Nene Creative | I68: Contexto Chuy | J68: No
A69: Gaming & Esports | B69: HyperX / Logitech G / Razer | C69: No | D69: Periféricos: categoría endémica gaming, deals de mid-budget rápidos | E69: Nene Creative | I69: Categoría endémica | J69: No
A70: Tech & Telecom | B70: Samsung México | C70: No | D70: Top anunciante tech MX; cliente de BWE (puerta indirecta) | E70: Nene Creative | F70: BWE Agency | I70: Branch Agencia, oct 2025 | J70: No
A71: Tech & Telecom | B71: Motorola / Xiaomi México | C71: No | D71: Retadores de volumen en smartphones; compran creators para lanzamientos | E71: Nene Creative | I71: Categoría | J71: No
A72: Financiero & Fintech | B72: Nu México / Klar / Stori | C72: No | D72: Neobancos en guerra de adquisición de usuarios; el patrón Velada (Revolut) aplica directo | E72: Mar Coronel | I72: Patrón categoría | J72: No
A73: Apuestas & Fantasy | B73: Stake | C73: Sí - activa | D73: Propuesta en HOLD: 8 historias + stream 1.5h (Nene, Ronny, Luis, Pamela, Rookie Leagues). Contacto: Carlos Vives | E73: Pool Combate (paquete) | G73: Carlos Vives | H73: Contacto comercial | I73: Tabulador Katana — VERIFICAR estatus | J73: Sí
A74: Apuestas & Fantasy | B74: 1win | C74: Sí - activa | D74: CERRADO: 3 stories con Mariel, Luis Pride, Ronaldo. Contacto: Leonardo Machado | E74: Pool Combate (paquete) | G74: Leonardo Machado | H74: Contacto comercial | I74: Tabulador — VERIFICAR | J74: Sí
A75: Apuestas & Fantasy | B75: Micasino | C75: Sí - activa | D75: Deals cerrados/finalizados (Luis Pride, Kike Padilla) — BUSCAR RENOVACIÓN | E75: Pool Combate (paquete) | G75: Adriani Romero / Leomearys | H75: Contacto comercial | I75: Tabulador — VERIFICAR | J75: Sí
A76: Apuestas & Fantasy | B76: Bet Master | C76: Sí - activa | D76: ALWAYS-ON mensual con Nikkole Teja. Contacto: Alexis | E76: Mariely | G76: Alexis | H76: Contacto comercial | I76: Tabulador — VERIFICAR | J76: Sí
A77: Apuestas & Fantasy | B77: Yowin | C77: Sí - pasada | D77: En hold — proponer otros talentos. Contacto: Inna | E77: Mar Coronel | G77: Inna | H77: Contacto comercial | I77: Tabulador — VERIFICAR | J77: Sí
A78: Apuestas & Fantasy | B78: TipsterPages | C78: Sí - pasada | D78: Cotizado: Canelo Angulo, Nene, Juan de Dios. Cliente natural para Mar Coronel (tipster) | E78: Mar Coronel | I78: Tabulador — VERIFICAR | J78: Sí
A79: Tech & Telecom | B79: Huawei | C79: Sí - pasada | D79: Deal FINALIZADO con Luis Pride — BUSCAR RENOVACIÓN. Contacto: Karina | E79: Pool Combate (paquete) | G79: Karina | H79: Contacto comercial | I79: Tabulador — VERIFICAR | J79: Sí
A80: Sportswear & Nutrición | B80: X Gear | C80: Sí - activa | D80: Cerrados: Mercedes Roa (1 TikTok pendiente) y Luis Pride (contenido pendiente). Contacto: Viridiana | E80: Pool Combate (paquete) | G80: Viridiana | H80: Contacto comercial | I80: Tabulador — VERIFICAR | J80: Sí
A81: Bebidas | B81: Aromante | C81: Sí - activa | D81: Cerrados: Juan de Dios + Selección (3 partidos). Contacto: Josué Suárez | E81: Varios / Pool mixto | G81: Josué Suárez | H81: Contacto comercial | I81: Tabulador — VERIFICAR | J81: Sí
A82: Bebidas | B82: Viuda de Romero (tequila) | C82: Sí - pasada | D82: Mega-propuesta embajadores 9 meses enviada ($4M por talento top) vía The Music Business Company (Jessica Sastre) | E82: Varios / Pool mixto | F82: The Music Business Company | G82: Jessica Sastre | H82: Contacto | I82: Tabulador — VERIFICAR | J82: Sí
A83: Belleza & Wellness | B83: Rexona (Unilever) | C83: Sí - pasada | D83: Propuesta embajadores 9 meses vía THNKY (Juan Prat): Rivaldios/Javetas/JuanDeDios | E83: Mariely | F83: THNKY | G83: Juan Prat | H83: Contacto agencia | I83: Tabulador — VERIFICAR | J83: Sí
A84: Alimentos & Gastro | B84: Barcel / Takis | C84: Sí - pasada | D84: Cotizaciones enviadas (Takis Hexa, Hot Nuts x Pal Norte vía MUNDUM) | E84: Varios / Pool mixto | F84: MUNDUM (Sebastián Vera) | I84: Tabulador — VERIFICAR | J84: Sí
A85: Alimentos & Gastro | B85: Burger King | C85: Sí - pasada | D85: Cotizado vía The Campaign Co (Yamileth Morales) | E85: Varios / Pool mixto | F85: The Campaign Co | G85: Yamileth Morales | H85: Contacto agencia | I85: Tabulador — VERIFICAR | J85: Sí
A86: Familia & Kids | B86: Temu | C86: Sí - pasada | D86: Cotización multi-talento enviada | E86: Varios / Pool mixto | I86: Tabulador — VERIFICAR | J86: Sí
A87: Familia & Kids | B87: eBay | C87: Sí - activa | D87: Cotizado: Canelo Angulo, Nene ($116k con IVA), Juan de Dios | E87: Nene Creative | I87: Tabulador — VERIFICAR | J87: Sí
A88: Streaming & Entretenimiento | B88: Supernova (evento) | C88: Sí - activa | D88: Deal CERRADO con Yoz Gless — relación directa con el ecosistema competidor/aliado | E88: Varios / Pool mixto | I88: Tabulador — VERIFICAR | J88: Sí
A89: Streaming & Entretenimiento | B89: Warner | C89: Sí - pasada | D89: Cotización multi-talento enviada | E89: Varios / Pool mixto | I89: Tabulador — VERIFICAR | J89: Sí

Sheet AGENCIAS
A1: SEÑALÉTICA: | B1: ACTIVO — ya hay contacto real / cerrado | C1: A UN PASO — contrato / por firmar | D1: EN PROCESO — negociación / propuesta / tibio | E1: FRÍO — target, aún sin contactar | F1: PERDIDO / DORMIDO — reactivar o descartar
A2: Agencia | B2: Tipo | C2: Marcas que maneja | D2: Ciudad | E2: Contacto clave | F2: Cargo | G2: Email | H2: LinkedIn | I2: ¿Relación previa? | J2: Notas | K2: Pasado a LEADS
A3: LePub Mexico City | B3: Agencia creativa | C3: Tecate (Heineken) — 20 medallas Clio 2026 | D3: CDMX | I3: No | J3: La agencia creativa más premiada de MX 2026. Puerta a Tecate. | K3: No
A4: BrandMe | B4: Agencia influencer mkt | C4: Disney, Jüsto, eBay, P&G, Domino's | D4: CDMX (Condesa) | I4: No | J4: Pionera en influencer mkt MX; plataforma + servicio 360. | K4: No
A5: Gamol | B5: Agencia influencer mkt | C5: Varios; "Best Influencer Agency" Fortune 2018-19 | D5: CDMX | I5: No | J5: Metodología de selección de talento; posible aliado o competencia. | K5: No
A6: Dinametra | B6: Agencia influencer mkt | C6: Red de 35,000+ influencers | D6: CDMX | I6: No | J6: Orientada a performance; YouTube/TikTok/Twitch. | K6: No
A7: INPULSE Digital | B7: Agencia influencer mkt | C7: Entretenimiento y música (LATAM/US) | D7: CDMX / Miami | I7: No | J7: Data + narrativa visual; fuerte en entertainment. | K7: No
A8: BWE Agency | B8: Agencia influencer mkt | C8: Rappi, Coca-Cola, Samsung | D8: CDMX | I8: No | J8: Puerta indirecta a Samsung y Coca-Cola. | K8: No
A9: SUBE | B9: Agencia de medios | C9: Retail, automotriz, turismo, fintech, APUESTAS | D9: CDMX / Miami / Dallas | I9: No | J9: Trabaja vertical de apuestas — cruce directo con pool combate y Mar Coronel. | K9: No
A10: another | B10: Agencia PR | C10: Comunicación estratégica + influencer + PR | D10: CDMX | I10: No | J10: Una de las más grandes de PR/comms en MX; mueve presupuestos de marcas premium. | K10: No
A11: GREY México | B11: Agencia creativa | C11: Varios (5 medallas Clio 2026) | D11: CDMX | I11: No | K11: No
A12: Wieden+Kennedy México | B12: Agencia creativa | C12: Marcas globales (3 medallas Clio 2026) | D12: CDMX | I12: No | J12: Agencia de Nike a nivel global. | K12: No
A13: DAVID The Agency | B13: Agencia creativa | C13: 4 medallas Clio 2026 | D13: CDMX | I13: No | K13: No
A14: VML México | B14: Agencia creativa | C14: Red global; múltiples cuentas de consumo | D14: CDMX | I14: No | K14: No
A15: GroupM (Mindshare / Wavemaker / EssenceMediacom) | B15: Agencia de medios | C15: Red WPP: maneja media de anunciantes top globales en MX | D15: CDMX | I15: No | J15: La red de medios más grande del mundo; sus planners deciden presupuestos de influencer/branded content. | K15: No
A16: OMD / PHD (Omnicom Media Group) | B16: Agencia de medios | C16: Anunciantes globales de consumo | D16: CDMX | I16: No | K16: No
A17: Starcom / Zenith (Publicis Media) | B17: Agencia de medios | C17: Anunciantes globales | D17: CDMX | I17: No | K17: No
A18: UM / Initiative (IPG Mediabrands) | B18: Agencia de medios | C18: Anunciantes globales | D18: CDMX | I18: No | K18: No
A19: Havas Media | B19: Agencia de medios | C19: Anunciantes globales y regionales | D19: CDMX | I19: No | K19: No
A20: Carat / iProspect (dentsu) | B20: Agencia de medios | C20: Anunciantes globales | D20: CDMX | I20: No | K20: No
A21: McCann México | B21: Agencia creativa | C21: Cuentas globales de consumo | D21: CDMX | E21: Dulce Torres | F21: Contacto | I21: Sí - activa | J21: Cliente activo: cotizaciones Solural y roster. VERIFICAR estatus. | K21: No
A22: Ogilvy México | B22: Agencia creativa | C22: Cuentas globales (1 medalla Clio 2026) | D22: CDMX | I22: No | K22: No
A23: BBDO México | B23: Agencia creativa | C23: Cuentas globales de consumo | D23: CDMX | I23: No | K23: No
A24: DDB México | B24: Agencia creativa | C24: Cuentas globales | D24: CDMX | I24: No | K24: No
A25: Leo Burnett México | B25: Agencia creativa | C25: Cuentas globales | D25: CDMX | I25: No | K25: No
A26: TBWA\Terán | B26: Agencia creativa | C26: Cuentas globales y locales | D26: CDMX | I26: No | J26: Histórica de MX. | K26: No
A27: Circus Marketing | B27: Agencia creativa | C27: Marcas de consumo y tech en LATAM | D27: CDMX | I27: No | J27: Independiente fuerte en LATAM, cultura digital. | K27: No
A28: Anónimo | B28: Agencia creativa | C28: Marcas MX | D28: CDMX | I28: No | J28: Independiente premiada. | K28: No
A29: Archer Troy | B29: Agencia creativa | C29: 2 medallas Clio 2026 | D29: CDMX | I29: No | K29: No
A30: GUT México | B30: Agencia creativa | C30: 2 medallas Clio 2026 | D30: CDMX | I30: No | J30: Independiente top LATAM. | K30: No
A31: Brands&People | B31: Agencia creativa | C31: 2 medallas Clio 2026 | D31: MTY/CDMX | I31: No | K31: No
A32: Boxer TTL | B32: Agencia creativa | C32: 3 medallas Clio 2026 | D32: CDMX | I32: No | K32: No
A33: MADE México | B33: Agencia creativa | C33: 1 medalla Clio 2026 | D33: CDMX | I33: No | K33: No
A34: Band of Insiders | B34: Agencia PR | C34: PR digital, tech y entretenimiento MX | D34: CDMX | E34: Kenia Mendiola | F34: Contacto | I34: Sí - activa | J34: YA TRABAJAMOS: campaña Tecate 0.0 cotizada mayo 2024. Puerta directa a Heineken. | K34: No
A35: MUNDUM | B35: Agencia influencer mkt | C35: Barcel (Hot Nuts x Pal Norte) | E35: Sebastián Vera | F35: Contacto | I35: Sí - pasada | J35: Cotización marzo 2024 — VERIFICAR | K35: Sí
A36: The Campaign Co | B36: Agencia influencer mkt | C36: Burger King | E36: Yamileth Morales | F36: Contacto | I36: Sí - pasada | J36: Tabulador — VERIFICAR | K36: Sí
A37: VKNG | B37: Agencia influencer mkt | C37: Amazon | I37: Sí - activa | J37: 3 campañas Ana Fer Lemus vía VKNG | K37: Sí
A38: THNKY | B38: Agencia creativa | C38: Rexona (Unilever) | E38: Juan Prat | F38: Contacto | I38: Sí - pasada | J38: Propuesta embajadores 2024 — VERIFICAR | K38: Sí
A39: The Music Business Company | B39: Agencia influencer mkt | C39: Viuda de Romero | E39: Jessica Sastre | F39: Contacto | I39: Sí - pasada | J39: Mega-propuesta 2024 — VERIFICAR | K39: Sí
A40: Latinfluence | B40: Agencia influencer mkt | C40: Filmora | I40: Sí - pasada | J40: Deal histórico (era Luisito Rey) | K40: No
A41: FCO Group (Afluency) | B41: Agencia influencer mkt | C41: Powerade | I41: Sí - activa | J41: Propuesta enviada: Mariel Estrella para Powerade, $130,000 MXN. Julio 2026. | K41: Sí
A42: Padrinito | B42: Agencia influencer mkt | C42: Canal MX | I42: Sí - activa | J42: Campaña de audio activa vía Ramiro: Wereverwero y Mike Máquina del Mal cerrados; Mercedes Roa y Marcela en proceso. Julio 2026. | K42: Sí

Sheet RED ALL STARS
A1: Nickname | B1: Nombre completo | C1: Rol/Posición | D1: Origen | E1: Estatus con Katana | F1: Potencial | G1: Notas
A2: GAMBETITI | B2: Fernando Alberto Valle Rios | C2: MC | D2: Culiacán | E2: Activo (adeudo pendiente) | F2: Fútbol-creator | G2: En gestión comercial con Steph/Ramiro; resolver adeudo
A3: LUISPRIDE | B3: Luis Aldo Escudero Romero | C3: MC | E3: Roster casa | F3: Combate MMA | G3: Peleó en Supernova Strikers 2025 (vs Shelao)
A4: RIVALDO | B4: Rivaldo Reatiga Ojeda | C4: DC | E4: Ex-talento (disputa/settlement) | G4: Obligación 140k/mes; con DW agency
A5: RONNY | B5: Ronaldo Taffarel Lopez Alonzo | C5: DFD | E5: Roster casa | F5: Combate Box
A6: NENE | B6: Nene Creative | E6: Roster casa | F6: Gaming #1 Rocket League | G6: Cuenta activa
A7: ES EL DAVO | B7: MC Davo | C7: MC | E7: Red All Stars | F7: Música/creator
A8: EDUIN | B8: Eduin Caz | E8: Red All Stars | F8: Música (Grupo Firme) | G8: Alto perfil
A9: LUIS R | B9: Luis R. Conriquez | E9: Red All Stars | F9: Música regional | G9: Alto perfil
A10: MALILLA | B10: El Malilla | E10: Red All Stars | F10: Música urbana | G10: Alto perfil
A11: YETUS | B11: Yetus | E11: Red All Stars | F11: Creator
A12: GRANADOS | B12: Ian Alejandro Granados Monteagudo | C12: DFC | E12: Red All Stars | F12: Creator | G12: Peleó preliminar Supernova 2025
A13: ROMAGOL | B13: Oscar Romario García Reyes | C13: DI | D13: CDMX | E13: Red All Stars | F13: Fútbol-creator
A14: FRANK H | B14: Jorge Francisco Espinoza Herrera | C14: MI | D14: Culiacán | E14: Red All Stars
A15: GABO | B15: Gabriel Montiel Gutierrez | C15: MC | E15: Red All Stars | F15: Creator (Werevertumorro crew)
A16: ALEMAN | B16: Erick Raúl Aleman Ramírez | E16: Red All Stars | F16: Música (Alemán) | G16: Cantó en Supernova 2025
A17: TASUKINHO | B17: Fernando Tasuko Sato Ramos | D17: Culiacán | E17: Red All Stars
A18: CANELO ANGULO | B18: Canelo Angulo | C18: DT | E18: Red All Stars | F18: Fútbol | G18: DT de All Stars
A19: MENDOZA | B19: Edwin Anuhar Mendoza Frias | C19: DD | D19: Monterrey | E19: Red All Stars
A20: GERA | B20: Gerardo Daniel Torres Montante | C20: MC | E20: Red All Stars
A21: MURGA RIOS | B21: Hugo Eduardo Murga Rios | C21: POR | E21: Red All Stars
A22: CHEYMAR | B22: Israel Gabriel Rivera | C22: MCD | E22: Red All Stars
A23: FIGURÓN | B23: Jesus Eduardo Elizondo Gutierrez | C23: DFC | E23: Red All Stars
A24: M.CELIS | B24: Manuel Francisco Celis Osuna | C24: E | D24: Culiacán | E24: Red All Stars
A25: MB | B25: Manuel Bernal García | C25: D | D25: Culiacán | E25: Red All Stars
A26: FT LEONEL | B26: Juan Leonel Ramirez Hernandez | D26: Culiacán | E26: Red All Stars
A27: AARON | B27: Aaron Antonio Bojorquez Beltran | C27: MC | D27: La Paz | E27: Red All Stars
A28: AMARAL | B28: Angel Omar Amaral Sepulveda | C28: DFD | D28: Culiacán | E28: Red All Stars

Sheet TARIFARIO KATANA
A1: Talento | B1: TikTok | C1: Reel IG | D1: Reel Collab | E1: TikTok + réplica Reel | F1: Post fijo IG | G1: Story | H1: Fijación 7 días | I1: Presencia evento | J1: Hosteo | K1: Stream evento | L1: Stream dedicado / hora | M1: Plataforma principal | N1: YouTube Short | O1: Integración YouTube | P1: Video dedicado YouTube | Q1: Podcast mensual | R1: Masterclass / experiencia | S1: Exclusividad mensual | T1: Fee pelea | U1: Audio musical TikTok | V1: Estado | W1: Notas | X1: Fuente / fecha
A2: Luis Pride | B2: 150000 | C2: 130000 | D2: 180000 | E2: =MAX(B2,C2)*1.5 -> 225000 | F2: 100000 | G2: 40000 | H2: 20000 | I2: 120000 | J2: N/A | K2: 75000 | L2: Caso por caso | M2: Por confirmar | N2: Pendiente | O2: Pendiente | P2: Pendiente | Q2: N/A | R2: 150000 | S2: 50000 | T2: 450000 | U2: Pendiente | V2: Activo | W2: Fee de pelea sujeto a evento y rival. | X2: Chuy, 31-jul-2026
A3: Ronny | B3: 90000 | C3: 130000 | D3: 150000 | E3: =MAX(B3,C3)*1.5 -> 195000 | F3: 80000 | G3: 40000 | H3: 15000 | I3: 100000 | J3: N/A | K3: 50000 | L3: Caso por caso | M3: Twitch principal | Kick disponible | N3: Pendiente | O3: Pendiente | P3: Pendiente | Q3: N/A | R3: 150000 | S3: 40000 | T3: 250000 | U3: Pendiente | V3: Activo | W3: Stream corresponde a Twitch. | X3: Chuy, 31-jul-2026
A4: Tejón de la Miel | B4: 100000 | C4: 150000 | D4: 180000 | E4: =MAX(B4,C4)*1.5 -> 225000 | F4: 80000 | G4: 40000 | H4: 15000 | I4: 100000 | J4: N/A | K4: N/A | L4: N/A | M4: N/A | N4: N/A | O4: N/A | P4: N/A | Q4: N/A | R4: 150000 | S4: 40000 | T4: 50000 | U4: Pendiente | V4: Activo | W4: Peleas desde $50,000. Menor de edad. | X4: Chuy, 31-jul-2026
A5: Divino Espinoza | B5: Caso por caso | C5: Caso por caso | D5: Caso por caso | E5: Caso por caso | F5: Caso por caso | G5: Caso por caso | H5: Caso por caso | I5: Caso por caso | J5: N/A | K5: N/A | L5: N/A | M5: N/A | N5: N/A | O5: N/A | P5: N/A | Q5: N/A | R5: Caso por caso | S5: Caso por caso | T5: 750000 | U5: Pendiente | V5: Activo | W5: $750,000 por marca en short durante combate. | X5: Chuy, 31-jul-2026
A6: Lazy Boy | B6: Caso por caso | C6: Caso por caso | D6: Caso por caso | E6: Caso por caso | F6: Caso por caso | G6: Caso por caso | H6: Caso por caso | I6: Caso por caso | J6: N/A | K6: N/A | L6: N/A | M6: N/A | N6: N/A | O6: N/A | P6: N/A | Q6: N/A | R6: Caso por caso | S6: Caso por caso | T6: Caso por caso | U6: Pendiente | V6: Activo | W6: Atleta de alto rendimiento; marca con afinidad. | X6: Chuy, 31-jul-2026
A7: César de la Parra | B7: Caso por caso | C7: Caso por caso | D7: Caso por caso | E7: Caso por caso | F7: Caso por caso | G7: Caso por caso | H7: Caso por caso | I7: Caso por caso | J7: Caso por caso | K7: N/A | L7: N/A | M7: N/A | N7: N/A | O7: N/A | P7: N/A | Q7: N/A | R7: Caso por caso | S7: Caso por caso | T7: N/A | U7: Pendiente | V7: Activo | W7: Solo marcas afines; priorizar anual o proyecto extraordinario. | X7: Chuy, 31-jul-2026
A8: Mariel Estrella | B8: 100000 | C8: Pendiente | D8: Pendiente | E8: Pendiente | F8: 80000 | G8: Pendiente | H8: Pendiente | I8: 100000 | J8: N/A | K8: Pendiente | L8: Pendiente | M8: Por confirmar | N8: Pendiente | O8: Pendiente | P8: Pendiente | Q8: N/A | R8: 150000 | S8: Pendiente | T8: N/A | U8: Pendiente | V8: Activo | W8: Faltan Reel, Story, fijación, stream y exclusividad. | X8: Chuy, 31-jul-2026
A9: Mariely Coronel | B9: 30000 | C9: 60000 | D9: 80000 | E9: =MAX(B9,C9)*1.5 -> 90000 | F9: 50000 | G9: 20000 | H9: 10000 | I9: 30000 | J9: N/A | K9: N/A | L9: N/A | M9: N/A | N9: N/A | O9: N/A | P9: N/A | Q9: N/A | R9: N/A | S9: 25000 | T9: N/A | U9: Pendiente | V9: Activo | W9: No stream, podcast ni masterclass por ahora. | X9: Chuy, 31-jul-2026
A10: Nene Creative | B10: 70000 | C10: 40000 | D10: 35000 | E10: =MAX(B10,C10)*1.5 -> 105000 | F10: 30000 | G10: 15000 | H10: 10000 | I10: 80000 | J10: N/A | K10: 60000 | L10: 120000 | M10: Twitch principal | Kick disponible | N10: 20000 | O10: 50000 | P10: 100000 | Q10: N/A | R10: 100000 | S10: 25000 | T10: N/A | U10: Pendiente | V10: Activo | W10: YouTube convertido a $20 MXN/USD. | X10: Chuy, 31-jul-2026
A11: Julio Orozco | B11: 30000 | C11: 70000 | D11: 100000 | E11: =MAX(B11,C11)*1.5 -> 105000 | F11: 50000 | G11: 30000 | H11: 20000 | I11: 60000 | J11: 80000 | K11: 50000 | L11: Caso por caso | M11: Kick principal | YouTube disponible | N11: Pendiente | O11: Pendiente | P11: Pendiente | Q11: 150000 | R11: N/A | S11: 40000 | T11: N/A | U11: Pendiente | V11: Activo | W11: Podcast mensual incluye 4 capítulos. | X11: Chuy, 31-jul-2026
A12: Juan de Dios García | B12: 200000 | C12: 160000 | D12: Pendiente | E12: =MAX(B12,C12)*1.5 -> 300000 | F12: 100000 | G12: 60000 | H12: 25000 | I12: 150000 | J12: N/A | K12: N/A | L12: N/A | M12: N/A | N12: N/A | O12: N/A | P12: N/A | Q12: N/A | R12: N/A | S12: 75000 | T12: N/A | U12: Pendiente | V12: Activo | W12: Falta definir Reel Collab. | X12: Chuy, 31-jul-2026
A13: Mamá Tejona | B13: 25000 | C13: 50000 | D13: 40000 | E13: =MAX(B13,C13)*1.5 -> 75000 | F13: 20000 | G13: 15000 | H13: 5000 | I13: 15000 | J13: N/A | K13: 15000 | L13: Caso por caso | M13: Por confirmar | N13: N/A | O13: N/A | P13: N/A | Q13: N/A | R13: N/A | S13: 10000 | T13: N/A | U13: Pendiente | V13: Activo | W13: Reel Collab quedó debajo del Reel IG; revisar. | X13: Chuy, 31-jul-2026
A14: Tony Gastélum | B14: 30000 | C14: 60000 | D14: Pendiente | E14: =MAX(B14,C14)*1.5 -> 90000 | F14: 40000 | G14: 25000 | H14: 10000 | I14: 50000 | J14: N/A | K14: 40000 | L14: 80000 | M14: Por confirmar | N14: Pendiente | O14: Pendiente | P14: Pendiente | Q14: N/A | R14: 100000 | S14: 25000 | T14: N/A | U14: Pendiente | V14: Activo | W14: Actual campeón mundial de calistenia. Falta Reel Collab. | X14: Chuy, 31-jul-2026
A15: Mike Máquina del Mal | B15: 100000 | C15: 50000 | D15: 60000 | E15: =MAX(B15,C15)*1.5 -> 150000 | F15: 60000 | G15: 30000 | H15: 15000 | I15: 80000 | J15: N/A | K15: Caso por caso | L15: 100000 | M15: YouTube Live principal | Twitch y Kick disponibles | N15: Pendiente | O15: Pendiente | P15: Pendiente | Q15: 150000 | R15: 100000 | S15: 40000 | T15: N/A | U15: Pendiente | V15: Activo | W15: Stream dedicado de marca: $100,000 por hora. | X15: Chuy, 31-jul-2026
A16: Gambetiti | B16: 100000 | C16: 70000 | D16: 85000 | E16: =MAX(B16,C16)*1.5 -> 150000 | F16: 80000 | G16: 25000 | H16: 10000 | I16: 60000 | J16: 30000 | K16: N/A | L16: N/A | M16: N/A | N16: N/A | O16: N/A | P16: N/A | Q16: N/A | R16: N/A | S16: 30000 | T16: N/A | U16: Pendiente | V16: Activo | W16: No realiza streams. Hosteo desde $30,000. | X16: Chuy, 31-jul-2026
A17: Neux | B17: 50000 | C17: 35000 | D17: 45000 | E17: =MAX(B17,C17)*1.5 -> 75000 | F17: 25000 | G17: 12000 | H17: 10000 | I17: 50000 | J17: N/A | K17: 40000 | L17: 70000 | M17: YouTube principal | Streaming por confirmar | N17: 40000 | O17: 60000 | P17: 100000 | Q17: N/A | R17: 50000 | S17: 20000 | T17: N/A | U17: Pendiente | V17: Activo | W17: Líder de nicho específico de gaming móvil. | X17: Chuy, 31-jul-2026
A18: Chuy Almada | B18: 100000 | C18: 120000 | D18: 140000 | E18: 160000 | F18: 80000 | G18: 25000 | H18: 10000 | I18: 100000 | J18: N/A | K18: N/A | L18: N/A | M18: YouTube principal | N18: 70000 | O18: 120000 | P18: 200000 | Q18: N/A | R18: Pendiente | S18: 40000 | T18: N/A | U18: Pendiente | V18: Activo | W18: YouTube es su producto premium. | X18: Chuy, 31-jul-2026
A19: Yoiker | B19: 25000 | C19: 40000 | D19: 35000 | E19: =MAX(B19,C19)*1.5 -> 60000 | F19: 30000 | G19: 20000 | H19: 10000 | I19: 50000 | J19: N/A | K19: 40000 | L19: 70000 | M19: Kick principal | Twitch disponible | N19: Pendiente | O19: Pendiente | P19: Pendiente | Q19: N/A | R19: 100000 | S19: 25000 | T19: N/A | U19: Pendiente | V19: Activo | W19: Integración dentro de stream: caso por caso. | X19: Chuy, 31-jul-2026
A20: Kike Padilla / Rookie Leagues | B20: 30000 | C20: 40000 | D20: 50000 | E20: =MAX(B20,C20)*1.5 -> 60000 | F20: 30000 | G20: 15000 | H20: 10000 | I20: 60000 | J20: 60000 | K20: 50000 | L20: 60000 | M20: Twitch | Kick | YouTube | N20: 20000 | O20: 25000 | P20: 40000 | Q20: N/A | R20: 60000 | S20: 30000 | T20: N/A | U20: Pendiente | V20: Activo | W20: Activación/experiencia de béisbol incluida en Masterclass/experiencia. | X20: Chuy, 31-jul-2026
A21: Stephany TV | B21: Pendiente | C21: Pendiente | D21: Pendiente | E21: Pendiente | F21: Pendiente | G21: Pendiente | H21: Pendiente | I21: Pendiente | J21: Pendiente | K21: Pendiente | L21: Pendiente | M21: Twitch / Kick — confirmar principal | N21: Pendiente | O21: Pendiente | P21: Pendiente | Q21: Pendiente | R21: Pendiente | S21: Pendiente | T21: N/A | U21: Pendiente | V21: Incompleto | W21: Falta tabulador completo y plataforma principal. | X21: Pendiente Chuy
A22: Padigol | B22: Pendiente | C22: Pendiente | D22: Pendiente | E22: Pendiente | F22: Pendiente | G22: Pendiente | H22: Pendiente | I22: Pendiente | J22: Pendiente | K22: Pendiente | L22: Pendiente | M22: Podcast / Video | N22: Pendiente | O22: Pendiente | P22: Pendiente | Q22: Pendiente | R22: Pendiente | S22: Pendiente | T22: N/A | U22: Pendiente | V22: CAPTURADO | W22: HISTÓRICO PRE-MUNDIAL; REQUIERE VALIDACIÓN ACTUAL. Canales Padigol: mención YouTube 1 = $55,000; paquete 15 menciones / 1 mes = $145,000; paquete 45 menciones / 3 meses = $255,000; TikTok 1 = $55,000; paquete 5 TikToks = $125,000; mención Facebook 1 = $35,000; paquete 5 = $110,000; paquete 10 = $200,000. Canales Podcast de Padilla: mención YouTube 1 = $75,000; paquete 13 menciones / 1 mes = $225,000; paquete 30 menciones / 3 meses = $420,000; livestream YouTube 1 = $70,000; Reel IG 1 = $75,000; paquete 5 Reels = $185,000; Story IG 1 = $75,000; paquete 5 Stories = $185,000; TikTok 1 = $75,000; paquete 5 TikToks = $185,000. Faltan páginas de Crónicas de Música y actualización posterior al Mundial. | X22: Capturas compartidas por Jesús Gallardo; tarifario fechado 22-mar-2026; cargado 2-ago-2026

Sheet PROPUESTAS KATANA ENGINE
A1: Folio | B1: Fecha | C1: Cliente | D1: Contacto cliente | E1: Agente / proveedor | F1: Contacto Katana | G1: Proyecto | H1: Tipo | I1: Estatus | J1: Vigencia | K1: Forma de pago | L1: Moneda / impuestos | M1: Alcance | N1: Talentos cotizados | O1: Perfiles por caso | P1: Aprobación requerida | Q1: Notas | R1: Última actualización
A2: KAT-VPV-2026-001 | B2: 31-jul-2026 | C2: Visit Puerto Vallarta | D2: Gloria | E2: Katana Talent | F2: Jesús Gallardo | G2: Talento, contenido y experiencias | H2: Propuesta comercial / tabulador | I2: Enviada | J2: 15 días naturales | K2: 50% anticipo y 50% finiquito al terminar | L2: MXN + IVA | M2: 1 Reel Collab + 5 Stories + fijación 7 días por talento. Sin total de paquete. | N2: Ronaldo BXM; Julio Orozco; Luis Pride; Mariel Estrella; Mariely Coronel; Tejón de la Miel; Mamá Tejona; Tony Gastélum; Yoiker; Nene Creative; Mike Máquina del Mal; Juan de Dios G; Kike Padilla / Rookie Leagues; Diego Alamillo; Neux | O2: Divino Espinoza; Lazy Boy; Chuy Almada; Diana; Padigol; Leandro Lasapa; Chanty; Supremo; Keizy; Rafe Lucado; César de la Parra; La Cotorrisa; Westcol; Ibai Llanos; Coscu | P2: Jesús Gallardo o Ramiro Ortiz antes de envío final | Q2: Propuesta enviada a Gloria. Dar seguimiento el martes 4 de agosto de 2026 a las 5:00 pm. No inventar métricas ni categorías. Yoiker: freestyle, lifestyle, entretenimiento y streaming. Tejón: combate (MMA y boxeo) y contenido familiar. Mariel Estrella: fitness y lifestyle. | R2: 02-ago-2026
A3: KAT-HON-2026-001 | B3: 02-ago-2026 | C3: HONOR | E3: Katana Talent | F3: Jesús Gallardo | G3: Propuesta y cotizaciones HONOR | H3: Propuesta comercial / cotización | I3: En desarrollo / por consolidar | M3: Recuperar y vincular propuesta y cotizaciones ya trabajadas. | P3: Jesús Gallardo o Ramiro Ortiz antes de envío final | Q3: Pendiente localizar archivos finales y confirmar versión maestra. | R3: 02-ago-2026
A4: KAT-NFX-2026-001 | B4: 02-ago-2026 | C4: Netflix | E4: Katana Talent | F4: Jesús Gallardo | G4: Propuesta Netflix | H4: Propuesta comercial | I4: En desarrollo / por consolidar | M4: Recuperar y vincular la propuesta trabajada. | P4: Jesús Gallardo o Ramiro Ortiz antes de envío final | Q4: Pendiente confirmar alcance, versión final y archivos asociados. | R4: 02-ago-2026
A5: KAT-UFC-2026-001 | B5: 02-ago-2026 | C5: UFC | E5: Katana Talent | F5: Jesús Gallardo | G5: Temporada UFC / Julio Orozco | H5: Propuesta comercial / relación de talento | I5: En desarrollo | M5: Organización de llamados, coordinación de talento y relación con UFC. | N5: Julio Orozco | P5: Jesús Gallardo o Ramiro Ortiz antes de envío final | Q5: Recuperar media kit, propuesta y documentos de relación UFC. | R5: 02-ago-2026
A6: KAT-PLR-2026-001 | B6: 02-ago-2026 | C6: The Player | E6: PARK8 | F6: Jesús Gallardo | G6: PARK8 × The Player — Creative Systems Development | H6: Propuesta comercial / Creative Tech Development | I6: En desarrollo — asignada a Jorge (Broly) y Tony | M6: Propuesta especializada en Creative Systems Development: Living Systems, Voice of the Garden (Jardín Botánico de Culiacán), personajes que bailan al ritmo de la música, Iris como IP propia y demostración en tiempo real. La página debe mostrar sistemas con lógica, reacción, comportamiento y generación de data; no efectos decorativos. | P6: Revisión estratégica por Jesús Gallardo y Ramiro Ortiz; validación técnica por Jorge (Broly) y Tony | Q6: Responsables de desarrollo: Jorge, también conocido como Broly, y Tony. Trabajar sobre el HTML existente y el prompt maestro. Reordenar la narrativa por capítulos: Voice of the Garden completo con data entregada al Jardín Botánico; personajes musicales; Iris como IP propia con demostración en tiempo real. Mantener Creative Tech Development como categoría amplia y Living Systems como diferenciador principal. Revisión de avance: miércoles 05-ago-2026 a las 12:00 pm. | R6: 03-ago-2026
A7: KAT-VDS-2026-001 | B7: 02-ago-2026 | C7: Viajes Lili | D7: Carolina Reséndiz | E7: Katana Talent | F7: Jesús Gallardo | G7: Viajes Lili — Strategic Talent & Travel Partnership | H7: Propuesta comercial / partnership | I7: Enviada | J7: 14 días naturales | K7: Por definir según cada colaboración | L7: MXN + IVA cuando aplique | M7: Partnership para integrar talento Katana, network regional y perfiles premium en viajes y experiencias. Valores comerciales como referencia; colaboraciones sujetas a cada oportunidad. | N7: Ronny; Julio Orozco; Luis Pride; Mariel Estrella; Mariely Coronel; Tejón de la Miel; Divino Espinoza; Lazy Boy; Nene Creative; Yoiker; Mike Máquina del Mal; Padigol; Neux; Tony Gastélum; Juan de Dios García; Kike Padilla / Rookie Leagues; Kamaka; Diego Alamillo; Leandro Lasapa; Chanty; Supremo; Keizy; Rafe Lucado | O7: César de la Parra; La Cotorrisa; Westcol; Ibai Llanos; Coscu | P7: Aprobada para envío por Jesús Gallardo | Q7: PDF enviado por WhatsApp a Carolina Reséndiz el 03-ago-2026. Enfoque: alianza estratégica de largo plazo, no cotización aislada. Seguimiento pendiente para conocer interés, destinos y próximos viajes. | R7: 03-ago-2026
A8: KAT-RON-2026-001 | B8: 02-ago-2026 | C8: Ronaldo BXM / Ronny | D8: Ronny | E8: Katana Talent | F8: Jesús Gallardo | G8: Propuesta privada de management | H8: Management / desarrollo de talento | I8: En desarrollo | J8: Sujeta a revisión y firma | K8: Por definir en contrato | L8: MXN + IVA cuando aplique | M8: Propuesta de management: historia compartida, activo actual, oportunidad, modelo de trabajo, plan inicial y siguiente paso contractual. | N8: Ronaldo BXM | O8: No aplica | P8: Jesús Gallardo o Ramiro Ortiz antes de envío final; contrato sujeto a revisión de JP | Q8: Caso piloto del Management Proposal Master. No mostrar tarifas, notas internas ni datos sensibles. HTML avanzado pendiente de identificar y vincular como master. | R8: 02-ago-2026
A9: KAT-AZT-2026-001 | B9: 03-ago-2026 | C9: TV Azteca / Azteca Peleas | D9: Jorge Garduño | E9: Katana Talent | F9: Jesús Gallardo | G9: Azteca Peleas — promoción digital — 03-oct-2026 | H9: Propuesta comercial / cotización | I9: Enviada | J9: 15 días naturales | K9: Anticipo y condiciones sujetas a contratación | L9: MXN + IVA | M9: Opciones independientes por talento: 1 Reel colaborativo + 4 Stories. Presencia en evento sujeta a disponibilidad y cotización adicional. | N9: Luis Pride; Tejón de la Miel; Chuy Almada; Ronny | O9: No aplica | P9: Aprobada para envío por Jesús Gallardo | Q9: PDF enviado a Jorge Garduño el 03-ago-2026. Valores cotizados: Luis Pride $340,000 + IVA; Tejón de la Miel $340,000 + IVA; Chuy Almada $400,000 + IVA; Ronny $310,000 + IVA. Propuesta sin descuento de paquete. Seguimiento: confirmar recepción, talento de interés y posibilidad presencial. | R9: 03-ago-2026

Sheet EXPEDIENTE PROPUESTAS
A1: Folio | B1: Cliente / proyecto | C1: Opportunity ID | D1: Brief / fuente | E1: Propuesta / HTML | F1: Cotización | G1: Contrato | H1: Carpeta Drive | I1: Media kits / assets | J1: Siguiente acción | K1: Próximo seguimiento | L1: Responsable | M1: Estado expediente | N1: Última actualización
A2: KAT-VPV-2026-001 | B2: Visit Puerto Vallarta — Talento, contenido y experiencias | C2: PENDIENTE | D2: PENDIENTE DE VINCULAR | E2: PENDIENTE DE VINCULAR | F2: PENDIENTE DE VINCULAR | G2: NO DISPONIBLE | H2: PENDIENTE DE VINCULAR | I2: PENDIENTE DE VINCULAR | J2: Dar seguimiento a Gloria | K2: 04-ago-2026 17:00 | L2: Jesús Gallardo | M2: INCOMPLETO | N2: 02-ago-2026
A3: KAT-HON-2026-001 | B3: HONOR — Propuesta y cotizaciones | C3: PENDIENTE | D3: PENDIENTE DE VINCULAR | E3: PENDIENTE DE LOCALIZAR | F3: PENDIENTE DE LOCALIZAR | G3: NO DISPONIBLE | H3: PENDIENTE DE VINCULAR | I3: PENDIENTE DE VINCULAR | J3: Localizar archivos finales y confirmar versión maestra | K3: PENDIENTE | L3: Jesús Gallardo | M3: INCOMPLETO | N3: 02-ago-2026
A4: KAT-NFX-2026-001 | B4: Netflix — Propuesta Netflix | C4: PENDIENTE | D4: PENDIENTE DE VINCULAR | E4: PENDIENTE DE LOCALIZAR | F4: NO DISPONIBLE | G4: NO DISPONIBLE | H4: PENDIENTE DE VINCULAR | I4: PENDIENTE DE VINCULAR | J4: Confirmar alcance y versión final | K4: PENDIENTE | L4: Jesús Gallardo | M4: INCOMPLETO | N4: 02-ago-2026
A5: KAT-UFC-2026-001 | B5: UFC — Temporada UFC / Julio Orozco | C5: PENDIENTE | D5: PENDIENTE DE VINCULAR | E5: PENDIENTE DE LOCALIZAR | F5: PENDIENTE | G5: PENDIENTE DE JP | H5: PENDIENTE DE VINCULAR | I5: PENDIENTE DE VINCULAR | J5: Recuperar media kit, propuesta y documentos UFC | K5: PENDIENTE | L5: Jesús Gallardo | M5: INCOMPLETO | N5: 02-ago-2026
A6: KAT-PLR-2026-001 | B6: The Player — PARK8 / Creative Tech | C6: PENDIENTE | D6: PENDIENTE DE VINCULAR | E6: PENDIENTE DE LOCALIZAR | F6: CASO POR CASO | G6: NO DISPONIBLE | H6: PENDIENTE DE VINCULAR | I6: PENDIENTE DE VINCULAR | J6: Recuperar pitch, prompts y materiales; no presentar DOPA sin claridad de participación | K6: PENDIENTE | L6: Jesús Gallardo | M6: REVISIÓN ESTRATÉGICA | N6: 02-ago-2026
A7: KAT-VDS-2026-001 | B7: Viajes Lili — Propuesta y cotización con talentos | C7: PENDIENTE | D7: PENDIENTE DE VINCULAR | E7: 85% — PENDIENTE DE VINCULAR | F7: 85% — PENDIENTE DE VINCULAR | G7: NO DISPONIBLE | H7: PENDIENTE DE VINCULAR | I7: PENDIENTE DE VINCULAR | J7: Cerrar propuesta y cotización, validar talentos y enviar | K7: PENDIENTE | L7: Jesús Gallardo | M7: EN PROCESO | N7: 02-ago-2026
A8: KAT-RON-2026-001 | B8: Ronaldo BXM — Propuesta privada de management | C8: KT-RONNY | D8: Roster + CRM + historial compartido | E8: HTML AVANZADO PENDIENTE DE IDENTIFICAR Y VINCULAR | F8: NO APLICA POR AHORA | G8: CONTRATO EN REVISIÓN DE JP | H8: Carpeta Ronaldo BXM localizada; pendiente confirmar carpeta maestra | I8: Media kits históricos localizados; assets avanzados pendientes de consolidar | J8: Identificar el HTML avanzado exacto y declararlo MANAGEMENT_PROPOSAL_MASTER | K8: PRIORIDAD ALTA | L8: Jesús Gallardo | M8: EN PROCESO — PILOTO | N8: 02-ago-2026

Sheet PRODUCCIÓN — EVENTOS
A1: KATANA ENGINE — MÓDULO PRODUCCIÓN Y CORRIDA FINANCIERA
A2: Este módulo registra y conecta cotizadores de producción. No sustituye cotizaciones vigentes de proveedores ni permite cotizar producción genéricamente.
A3: ASSET_ID | B3: NOMBRE | C3: TIPO | D3: USO | E3: ESTADO | F3: FECHA BASE | G3: FUENTE | H3: LINK | I3: RESPONSABLE | J3: VALIDACIÓN | K3: NOTAS | L3: VENUE | M3: CIUDAD | N3: AFORO | O3: PROVEEDORES | P3: PRÓXIMA ACCIÓN
A4: PROD-001 | B4: KATANA_EVENTOS | C4: Corrida financiera de eventos | D4: Escenarios de boletaje, patrocinios, costos, impuestos, inversión y utilidad | E4: CAPTURADO | F4: Histórico 2022–2025 | G4: Google Sheets | H4: https://docs.google.com/spreadsheets/d/19pVdjkzapM8j5WxR3y2D7i41gEddaTFFWfsQ5nrjI7w | I4: PENDIENTE | J4: REQUIERE VALIDACIÓN | K4: La estructura es útil. Los costos, proveedores, impuestos y supuestos son históricos y no deben usarse como cotización vigente. Contiene escenarios por aforo y hojas por evento. | L4: Variable por evento | M4: Variable por evento | N4: Variable por evento | O4: REQUIERE COTIZACIÓN ACTUAL | P4: Auditar fórmulas y crear plantilla limpia 2026
A5: COT-LEG-001 | B5: TEMPLATE_Cotizador_Katana | C5: Cotizador comercial / booking | D5: Cotizaciones de talento y booking | E5: HISTÓRICO | F5: 2019–2022 / copia 2026 | G5: Google Sheets | H5: https://docs.google.com/spreadsheets/d/1yGIGsGjflsD2JIz24hwgq2Qbtt1LVS94agwK7muJVns | I5: PENDIENTE | J5: NO USAR COMO FUENTE DE TARIFAS | K5: Tiene BOOKING, CRM, Directorio y formatos de cotización. No es corrida financiera de producción y no sustituye el Tarifario Katana actual.
A6: COT-LEG-002 | B6: COTIZADOR 2023 | C6: Archivo histórico de cotizaciones | D6: Referencia de formatos y casos anteriores | E6: ARCHIVO HISTÓRICO | F6: 2023 | G6: Google Sheets | H6: https://docs.google.com/spreadsheets/d/19Dmjn7QzesLSTtPyfnnceYgsQrbYkWZtWrIAYguTISc | I6: PENDIENTE | J6: NO USAR COMO FUENTE DE TARIFAS | K6: Contiene numerosos cotizadores, CRM antiguos, tabuladores y casos. Sirve como archivo y referencia, no como sistema operativo actual.

Sheet TALENT ASSETS
